{
    "schema_version": "fotmob_strict_fixture_identity_guard_implementation_adg9_v1",
    "phase": "Phase 5.21-ADG9",
    "generated_at": "2026-05-28T10:09:51.147Z",
    "adg9_guard_execution_status": "completed_strict_fixture_identity_guard_validation",
    "runtime_code_changed": true,
    "guard_function": "validateStrictFixtureIdentity",
    "guard_location": "src/infrastructure/services/FotMobRouteIdentityReconciler.js",
    "guard_implemented": true,
    "no_live_fetch": true,
    "no_network_request": true,
    "no_browser_automation": true,
    "no_direct_api_probing": true,
    "no_db_write": true,
    "no_raw_write": true,
    "no_raw_match_data_insert": true,
    "no_re_acceptance": true,
    "no_suspension_reversal": true,
    "no_source_inventory_mutation": true,
    "no_candidate_mutation": true,
    "no_full_payload_saved": true,
    "raw_write_execution_ready": false,
    "audited_sample_count": 8,
    "positive_control_count": 1,
    "guard_passed_count": 1,
    "guard_blocked_count": 7,
    "reverse_fixture_mapping_error_count": 5,
    "home_away_inversion_count": 5,
    "same_team_pair_wrong_leg_count": 7,
    "date_mismatch_count": 7,
    "suspended_reference_still_blocked_count": 2,
    "correction_candidate_count": 5,
    "guard_adg8_consistent_count": 8,
    "guard_details": [
        {
            "fixture_identity_guard_status": "passed",
            "fixture_identity_guard_reason": null,
            "audit_classification": "correct_mapping",
            "schedule_external_id": "4813735",
            "detail_external_id_candidate": "4813735",
            "rejected_detail_external_id_candidate": null,
            "observed_reversed_detail_id": null,
            "observed_detail_id": "4813735",
            "expected_home_team": "afc bournemouth",
            "expected_away_team": "manchester city",
            "observed_home_team": "afc bournemouth",
            "observed_away_team": "manchester city",
            "expected_match_date": null,
            "observed_match_date": "Tue, May 19, 2026, 18:30 UTC",
            "expected_competition": null,
            "observed_competition": null,
            "expected_season": null,
            "observed_season": null,
            "home_away_orientation_status": "matches",
            "team_pair_match": true,
            "date_delta_days": null,
            "date_within_tolerance": false,
            "competition_match": false,
            "season_match": false,
            "detail_identity_candidate_validated": true,
            "url_hash_alone_insufficient": false,
            "correction_needed": false,
            "correction_type": null,
            "correction_actions": [],
            "raw_write_execution_ready": false,
            "is_suspended_reference": false,
            "blockers": [],
            "target_match_id": null,
            "adg8_audit_classification": "correct_mapping",
            "guard_consistent_with_adg8": true,
            "source_page_url": "https://www.fotmob.com/zh-Hans/matches/manchester-city-vs-afc-bournemouth/2feiv3#4813735",
            "source_inventory_record_key": null,
            "candidate_generation_rule": "url_hash_fragment_candidate_without_strict_fixture_guard"
        },
        {
            "fixture_identity_guard_status": "blocked",
            "fixture_identity_guard_reason": "home_away_inversion_with_date_mismatch_indicates_reverse_fixture_not_this_target",
            "audit_classification": "reverse_fixture_mapping_error",
            "schedule_external_id": "4830458",
            "detail_external_id_candidate": "4830458",
            "rejected_detail_external_id_candidate": "4830458",
            "observed_reversed_detail_id": "4830627",
            "observed_detail_id": "4830627",
            "expected_home_team": "angers",
            "expected_away_team": "paris fc",
            "observed_home_team": "paris fc",
            "observed_away_team": "angers",
            "expected_match_date": "2025-08-17T15:15:00.000Z",
            "observed_match_date": "Sun, Jan 25, 2026, 16:15 UTC",
            "expected_competition": "ligue 1",
            "observed_competition": null,
            "expected_season": null,
            "observed_season": null,
            "home_away_orientation_status": "reversed",
            "team_pair_match": true,
            "date_delta_days": 161,
            "date_within_tolerance": false,
            "competition_match": false,
            "season_match": false,
            "detail_identity_candidate_validated": false,
            "url_hash_alone_insufficient": false,
            "correction_needed": true,
            "correction_type": "reject_candidate",
            "correction_actions": [
                "reject_candidate",
                "supersede_candidate",
                "require_new_source_inventory_record",
                "require_strict_home_away_date_guard"
            ],
            "raw_write_execution_ready": false,
            "is_suspended_reference": false,
            "blockers": [
                "home_away_inversion",
                "date_mismatch",
                "same_team_pair_wrong_leg"
            ],
            "target_match_id": "53_20252026_4830458",
            "adg8_audit_classification": "reverse_fixture_mapping_error",
            "guard_consistent_with_adg8": true,
            "source_page_url": "https://www.fotmob.com/matches/paris-fc-vs-angers/1qlitv#4830458",
            "source_inventory_record_key": "l1_api_data_leagues:overview.leagueOverviewMatches.5:4830458",
            "candidate_generation_rule": "url_hash_fragment_candidate_without_strict_fixture_guard"
        },
        {
            "fixture_identity_guard_status": "blocked",
            "fixture_identity_guard_reason": "home_away_inversion_with_date_mismatch_indicates_reverse_fixture_not_this_target",
            "audit_classification": "reverse_fixture_mapping_error",
            "schedule_external_id": "4830459",
            "detail_external_id_candidate": "4830459",
            "rejected_detail_external_id_candidate": "4830459",
            "observed_reversed_detail_id": "4830667",
            "observed_detail_id": "4830667",
            "expected_home_team": "auxerre",
            "expected_away_team": "lorient",
            "observed_home_team": "lorient",
            "observed_away_team": "auxerre",
            "expected_match_date": "2025-08-17T15:15:00.000Z",
            "observed_match_date": "Sun, Mar 1, 2026, 16:15 UTC",
            "expected_competition": "ligue 1",
            "observed_competition": null,
            "expected_season": null,
            "observed_season": null,
            "home_away_orientation_status": "reversed",
            "team_pair_match": true,
            "date_delta_days": 196,
            "date_within_tolerance": false,
            "competition_match": false,
            "season_match": false,
            "detail_identity_candidate_validated": false,
            "url_hash_alone_insufficient": false,
            "correction_needed": true,
            "correction_type": "reject_candidate",
            "correction_actions": [
                "reject_candidate",
                "supersede_candidate",
                "require_new_source_inventory_record",
                "require_strict_home_away_date_guard"
            ],
            "raw_write_execution_ready": false,
            "is_suspended_reference": false,
            "blockers": [
                "home_away_inversion",
                "date_mismatch",
                "same_team_pair_wrong_leg"
            ],
            "target_match_id": "53_20252026_4830459",
            "adg8_audit_classification": "reverse_fixture_mapping_error",
            "guard_consistent_with_adg8": true,
            "source_page_url": "https://www.fotmob.com/matches/auxerre-vs-lorient/2gteq5#4830459",
            "source_inventory_record_key": "l1_api_data_leagues:overview.leagueOverviewMatches.6:4830459",
            "candidate_generation_rule": "url_hash_fragment_candidate_without_strict_fixture_guard"
        },
        {
            "fixture_identity_guard_status": "blocked",
            "fixture_identity_guard_reason": "home_away_inversion_with_date_mismatch_indicates_reverse_fixture_not_this_target",
            "audit_classification": "reverse_fixture_mapping_error",
            "schedule_external_id": "4830460",
            "detail_external_id_candidate": "4830460",
            "rejected_detail_external_id_candidate": "4830460",
            "observed_reversed_detail_id": "4830648",
            "observed_detail_id": "4830648",
            "expected_home_team": "brest",
            "expected_away_team": "lille",
            "observed_home_team": "lille",
            "observed_away_team": "brest",
            "expected_match_date": "2025-08-17T13:00:00.000Z",
            "observed_match_date": "Sat, Feb 14, 2026, 18:00 UTC",
            "expected_competition": "ligue 1",
            "observed_competition": null,
            "expected_season": null,
            "observed_season": null,
            "home_away_orientation_status": "reversed",
            "team_pair_match": true,
            "date_delta_days": 181,
            "date_within_tolerance": false,
            "competition_match": false,
            "season_match": false,
            "detail_identity_candidate_validated": false,
            "url_hash_alone_insufficient": false,
            "correction_needed": true,
            "correction_type": "reject_candidate",
            "correction_actions": [
                "reject_candidate",
                "supersede_candidate",
                "require_new_source_inventory_record",
                "require_strict_home_away_date_guard"
            ],
            "raw_write_execution_ready": false,
            "is_suspended_reference": false,
            "blockers": [
                "home_away_inversion",
                "date_mismatch",
                "same_team_pair_wrong_leg"
            ],
            "target_match_id": "53_20252026_4830460",
            "adg8_audit_classification": "reverse_fixture_mapping_error",
            "guard_consistent_with_adg8": true,
            "source_page_url": "https://www.fotmob.com/matches/brest-vs-lille/2fo2ub#4830460",
            "source_inventory_record_key": "l1_api_data_leagues:overview.leagueOverviewMatches.4:4830460",
            "candidate_generation_rule": "url_hash_fragment_candidate_without_strict_fixture_guard"
        },
        {
            "fixture_identity_guard_status": "blocked",
            "fixture_identity_guard_reason": "home_away_inversion_with_date_mismatch_indicates_reverse_fixture_not_this_target",
            "audit_classification": "reverse_fixture_mapping_error",
            "schedule_external_id": "4830462",
            "detail_external_id_candidate": "4830462",
            "rejected_detail_external_id_candidate": "4830462",
            "observed_reversed_detail_id": "4830618",
            "observed_detail_id": "4830618",
            "expected_home_team": "metz",
            "expected_away_team": "strasbourg",
            "observed_home_team": "strasbourg",
            "observed_away_team": "metz",
            "expected_match_date": "2025-08-17T15:15:00.000Z",
            "observed_match_date": "Sun, Jan 18, 2026, 14:00 UTC",
            "expected_competition": "ligue 1",
            "observed_competition": null,
            "expected_season": null,
            "observed_season": null,
            "home_away_orientation_status": "reversed",
            "team_pair_match": true,
            "date_delta_days": 154,
            "date_within_tolerance": false,
            "competition_match": false,
            "season_match": false,
            "detail_identity_candidate_validated": false,
            "url_hash_alone_insufficient": false,
            "correction_needed": true,
            "correction_type": "reject_candidate",
            "correction_actions": [
                "reject_candidate",
                "supersede_candidate",
                "require_new_source_inventory_record",
                "require_strict_home_away_date_guard"
            ],
            "raw_write_execution_ready": false,
            "is_suspended_reference": false,
            "blockers": [
                "home_away_inversion",
                "date_mismatch",
                "same_team_pair_wrong_leg"
            ],
            "target_match_id": "53_20252026_4830462",
            "adg8_audit_classification": "reverse_fixture_mapping_error",
            "guard_consistent_with_adg8": true,
            "source_page_url": "https://www.fotmob.com/matches/metz-vs-strasbourg/2srvl5#4830462",
            "source_inventory_record_key": "l1_api_data_leagues:overview.leagueOverviewMatches.7:4830462",
            "candidate_generation_rule": "url_hash_fragment_candidate_without_strict_fixture_guard"
        },
        {
            "fixture_identity_guard_status": "blocked",
            "fixture_identity_guard_reason": "home_away_inversion_with_date_mismatch_indicates_reverse_fixture_not_this_target",
            "audit_classification": "reverse_fixture_mapping_error",
            "schedule_external_id": "4830464",
            "detail_external_id_candidate": "4830464",
            "rejected_detail_external_id_candidate": "4830464",
            "observed_reversed_detail_id": "4830689",
            "observed_detail_id": "4830689",
            "expected_home_team": "nantes",
            "expected_away_team": "paris saint-germain",
            "observed_home_team": "paris saint-germain",
            "observed_away_team": "nantes",
            "expected_match_date": "2025-08-17T18:45:00.000Z",
            "observed_match_date": "Wed, Apr 22, 2026, 17:00 UTC",
            "expected_competition": "ligue 1",
            "observed_competition": null,
            "expected_season": null,
            "observed_season": null,
            "home_away_orientation_status": "reversed",
            "team_pair_match": true,
            "date_delta_days": 248,
            "date_within_tolerance": false,
            "competition_match": false,
            "season_match": false,
            "detail_identity_candidate_validated": false,
            "url_hash_alone_insufficient": false,
            "correction_needed": true,
            "correction_type": "reject_candidate",
            "correction_actions": [
                "reject_candidate",
                "supersede_candidate",
                "require_new_source_inventory_record",
                "require_strict_home_away_date_guard"
            ],
            "raw_write_execution_ready": false,
            "is_suspended_reference": false,
            "blockers": [
                "home_away_inversion",
                "date_mismatch",
                "same_team_pair_wrong_leg"
            ],
            "target_match_id": "53_20252026_4830464",
            "adg8_audit_classification": "reverse_fixture_mapping_error",
            "guard_consistent_with_adg8": true,
            "source_page_url": "https://www.fotmob.com/matches/nantes-vs-paris-saint-germain/379ruy#4830464",
            "source_inventory_record_key": "l1_api_data_leagues:overview.leagueOverviewMatches.8:4830464",
            "candidate_generation_rule": "url_hash_fragment_candidate_without_strict_fixture_guard"
        },
        {
            "fixture_identity_guard_status": "blocked",
            "fixture_identity_guard_reason": "suspended_reference_cannot_be_reactivated_by_guard",
            "audit_classification": "suspended_reference_still_blocked",
            "schedule_external_id": "4830461",
            "detail_external_id_candidate": "4830461",
            "rejected_detail_external_id_candidate": null,
            "observed_reversed_detail_id": "4830758",
            "observed_detail_id": "4830758",
            "expected_home_team": "lens",
            "expected_away_team": "lyon",
            "observed_home_team": "lyon",
            "observed_away_team": "lens",
            "expected_match_date": "2025-08-16T15:00:00.000Z",
            "observed_match_date": "Sun, May 17, 2026, 19:00 UTC",
            "expected_competition": "ligue 1",
            "observed_competition": null,
            "expected_season": null,
            "observed_season": null,
            "home_away_orientation_status": "reversed",
            "team_pair_match": true,
            "date_delta_days": 274,
            "date_within_tolerance": false,
            "competition_match": false,
            "season_match": false,
            "detail_identity_candidate_validated": false,
            "url_hash_alone_insufficient": false,
            "correction_needed": false,
            "correction_type": null,
            "correction_actions": [],
            "raw_write_execution_ready": false,
            "is_suspended_reference": true,
            "blockers": [
                "suspended_reference_still_blocked",
                "home_away_inversion",
                "date_mismatch",
                "same_team_pair_wrong_leg"
            ],
            "target_match_id": "53_20252026_4830461",
            "adg8_audit_classification": "suspended_reference_still_blocked",
            "guard_consistent_with_adg8": true,
            "source_page_url": "https://www.fotmob.com/matches/lens-vs-lyon/2s3gtg#4830461",
            "source_inventory_record_key": "l1_api_data_leagues:overview.leagueOverviewMatches.1:4830461",
            "candidate_generation_rule": "url_hash_fragment_candidate_without_strict_fixture_guard"
        },
        {
            "fixture_identity_guard_status": "blocked",
            "fixture_identity_guard_reason": "suspended_reference_cannot_be_reactivated_by_guard",
            "audit_classification": "suspended_reference_still_blocked",
            "schedule_external_id": "4830463",
            "detail_external_id_candidate": "4830463",
            "rejected_detail_external_id_candidate": null,
            "observed_reversed_detail_id": "4830622",
            "observed_detail_id": "4830622",
            "expected_home_team": "monaco",
            "expected_away_team": "le havre",
            "observed_home_team": "le havre",
            "observed_away_team": "monaco",
            "expected_match_date": "2025-08-16T17:00:00.000Z",
            "observed_match_date": "Sat, Jan 24, 2026, 18:00 UTC",
            "expected_competition": "ligue 1",
            "observed_competition": null,
            "expected_season": null,
            "observed_season": null,
            "home_away_orientation_status": "reversed",
            "team_pair_match": true,
            "date_delta_days": 161,
            "date_within_tolerance": false,
            "competition_match": false,
            "season_match": false,
            "detail_identity_candidate_validated": false,
            "url_hash_alone_insufficient": false,
            "correction_needed": false,
            "correction_type": null,
            "correction_actions": [],
            "raw_write_execution_ready": false,
            "is_suspended_reference": true,
            "blockers": [
                "suspended_reference_still_blocked",
                "home_away_inversion",
                "date_mismatch",
                "same_team_pair_wrong_leg"
            ],
            "target_match_id": "53_20252026_4830463",
            "adg8_audit_classification": "suspended_reference_still_blocked",
            "guard_consistent_with_adg8": true,
            "source_page_url": "https://www.fotmob.com/matches/le-havre-vs-monaco/362v61#4830463",
            "source_inventory_record_key": "l1_api_data_leagues:overview.leagueOverviewMatches.2:4830463",
            "candidate_generation_rule": "url_hash_fragment_candidate_without_strict_fixture_guard"
        }
    ]
}
