{
  "match_id": "4803125",
  "fotmob_id": "4803125",
  "home_team": "Lecce",
  "away_team": "Napoli",
  "home_score": 0,
  "away_score": 1,
  "status": "finished",
  "home_stats": {
    "possession": 41.0,
    "shots": 2,
    "shots_on_target": 2,
    "corners": 3,
    "fouls": 10,
    "offsides": 1,
    "yellow_cards": 2,
    "red_cards": 0,
    "saves": 2,
    "expected_goals": 0.95,
    "big_chances_created": 1,
    "big_chances_missed": 1,
    "passes": 291,
    "tackles": 29,
    "interceptions": 9
  },
  "away_stats": {
    "possession": 59.0,
    "shots": 5,
    "shots_on_target": 3,
    "corners": 5,
    "fouls": 14,
    "offsides": 0,
    "yellow_cards": 1,
    "red_cards": 0,
    "saves": 2,
    "expected_goals": 1.09,
    "big_chances_created": 1,
    "big_chances_missed": 1,
    "passes": 452,
    "tackles": 23,
    "interceptions": 11
  },
  "events": [],
  "shot_map": [
    {
      "minute": 4,
      "player_name": "Lorenzo Lucca",
      "team_id": "9875",
      "x": 77.1917475744,
      "y": 31.48375,
      "is_on_target": true,
      "expected_goals": 0.014942136593163013,
      "shot_type": "RightFoot",
      "is_goal": false,
      "is_blocked": false
    },
    {
      "minute": 12,
      "player_name": "Billy Gilmour",
      "team_id": "9875",
      "x": 78.9936893216,
      "y": 34.99125,
      "is_on_target": true,
      "expected_goals": 0.01438672374933958,
      "shot_type": "RightFoot",
      "is_goal": false,
      "is_blocked": false
    },
    {
      "minute": 16,
      "player_name": "Mathias Olivera",
      "team_id": "9875",
      "x": 100.5431034486,
      "y": 27.698571428000005,
      "is_on_target": false,
      "expected_goals": 0.11624865233898163,
      "shot_type": "Header",
      "is_goal": false,
      "is_blocked": false
    },
    {
      "minute": 18,
      "player_name": "Matteo Politano",
      "team_id": "9875",
      "x": 91.7,
      "y": 19.515159238299997,
      "is_on_target": true,
      "expected_goals": 0.056911613792181015,
      "shot_type": "LeftFoot",
      "is_goal": false,
      "is_blocked": false
    },
    {
      "minute": 26,
      "player_name": "Medon Berisha",
      "team_id": "9888",
      "x": 89.1,
      "y": 31.636249999999997,
      "is_on_target": false,
      "expected_goals": 0.0951547622680664,
      "shot_type": "RightFoot",
      "is_goal": false,
      "is_blocked": false
    },
    {
      "minute": 30,
      "player_name": "Matteo Politano",
      "team_id": "9875",
      "x": 96.2192982446,
      "y": 21.4769426787,
      "is_on_target": false,
      "expected_goals": 0.04607297480106354,
      "shot_type": "LeftFoot",
      "is_goal": false,
      "is_blocked": false
    },
    {
      "minute": 35,
      "player_name": "Mathias Olivera",
      "team_id": "9875",
      "x": 100.8275862072,
      "y": 44.000764326500004,
      "is_on_target": true,
      "expected_goals": 0.11963395029306412,
      "shot_type": "LeftFoot",
      "is_goal": false,
      "is_blocked": false
    },
    {
      "minute": 36,
      "player_name": "Billy Gilmour",
      "team_id": "9875",
      "x": 90.2,
      "y": 44.6313375752,
      "is_on_target": true,
      "expected_goals": 0.02637464925646782,
      "shot_type": "RightFoot",
      "is_goal": false,
      "is_blocked": false
    },
    {
      "minute": 36,
      "player_name": "Lorenzo Lucca",
      "team_id": "9875",
      "x": 95.0614035074,
      "y": 30.492499999999996,
      "is_on_target": false,
      "expected_goals": 0.07020701467990875,
      "shot_type": "RightFoot",
      "is_goal": false,
      "is_blocked": false
    },
    {
      "minute": 47,
      "player_name": "Tiago Gabriel",
      "team_id": "9888",
      "x": 99.50000000040001,
      "y": 34.68625,
      "is_on_target": false,
      "expected_goals": 0.1542559415102005,
      "shot_type": "Header",
      "is_goal": false,
      "is_blocked": false
    },
    {
      "minute": 49,
      "player_name": "Matteo Politano",
      "team_id": "9875",
      "x": 76.5160194192,
      "y": 12.6593365003,
      "is_on_target": false,
      "expected_goals": 0.014453034847974777,
      "shot_type": "LeftFoot",
      "is_goal": false,
      "is_blocked": false
    },
    {
      "minute": 51,
      "player_name": "Kialonda Gaspar",
      "team_id": "9888",
      "x": 95.640350876,
      "y": 35.3725,
      "is_on_target": true,
      "expected_goals": 0.042542483657598495,
      "shot_type": "Header",
      "is_goal": false,
      "is_blocked": false
    },
    {
      "minute": 56,
      "player_name": "Francesco Camarda",
      "team_id": "9888",
      "x": 94.0,
      "y": 34.0,
      "is_on_target": true,
      "expected_goals": 0.7884,
      "shot_type": "RightFoot",
      "is_goal": false,
      "is_blocked": false
    },
    {
      "minute": 61,
      "player_name": "Medon Berisha",
      "team_id": "9888",
      "x": 95.0614035074,
      "y": 10.0356398163,
      "is_on_target": true,
      "expected_goals": 0.03989366814494133,
      "shot_type": "RightFoot",
      "is_goal": false,
      "is_blocked": false
    },
    {
      "minute": 67,
      "player_name": "Juan Jesus",
      "team_id": "9875",
      "x": 98.0526315785,
      "y": 30.568749999999998,
      "is_on_target": true,
      "expected_goals": 0.081509530544281,
      "shot_type": "Header",
      "is_goal": false,
      "is_blocked": false
    },
    {
      "minute": 69,
      "player_name": "Andre-Frank Zambo Anguissa",
      "team_id": "9875",
      "x": 97.8596491223,
      "y": 34.1525,
      "is_on_target": true,
      "expected_goals": 0.11622188240289688,
      "shot_type": "Header",
      "is_goal": true,
      "is_blocked": false
    },
    {
      "minute": 71,
      "player_name": "Eljif Elmas",
      "team_id": "9875",
      "x": 81.471359224,
      "y": 36.8975,
      "is_on_target": false,
      "expected_goals": 0.06277154386043549,
      "shot_type": "RightFoot",
      "is_goal": false,
      "is_blocked": false
    },
    {
      "minute": 72,
      "player_name": "Lassana Coulibaly",
      "team_id": "9888",
      "x": 97.1842105256,
      "y": 25.53375,
      "is_on_target": true,
      "expected_goals": 0.02236674726009369,
      "shot_type": "Header",
      "is_goal": false,
      "is_blocked": false
    },
    {
      "minute": 75,
      "player_name": "Medon Berisha",
      "team_id": "9888",
      "x": 61.1416666665,
      "y": 36.440000000000005,
      "is_on_target": false,
      "expected_goals": 0.02071552723646164,
      "shot_type": "RightFoot",
      "is_goal": false,
      "is_blocked": false
    },
    {
      "minute": 89,
      "player_name": "Giovanni Di Lorenzo",
      "team_id": "9875",
      "x": 90.3,
      "y": 26.4009375,
      "is_on_target": true,
      "expected_goals": 0.06601494550704956,
      "shot_type": "RightFoot",
      "is_goal": false,
      "is_blocked": false
    },
    {
      "minute": 90,
      "player_name": "Giovanni Di Lorenzo",
      "team_id": "9875",
      "x": 84.7373786408,
      "y": 20.2858598756,
      "is_on_target": true,
      "expected_goals": 0.023750076070427895,
      "shot_type": "LeftFoot",
      "is_goal": false,
      "is_blocked": false
    }
  ],
  "player_ratings": {},
  "data_source": "fotmob",
  "collected_at": "2025-12-11T03:38:37.873400+00:00",
  "data_completeness_score": 0.599
}