{
  "match_id": "4803146",
  "fotmob_id": "4803146",
  "home_team": "Pisa",
  "away_team": "Cremonese",
  "home_score": 1,
  "away_score": 0,
  "status": "finished",
  "home_stats": {
    "possession": 38.0,
    "shots": 2,
    "shots_on_target": 6,
    "corners": 4,
    "fouls": 11,
    "offsides": 2,
    "yellow_cards": 4,
    "red_cards": 0,
    "saves": 3,
    "expected_goals": 0.95,
    "big_chances_created": 4,
    "big_chances_missed": 3,
    "passes": 226,
    "tackles": 19,
    "interceptions": 8
  },
  "away_stats": {
    "possession": 62.0,
    "shots": 4,
    "shots_on_target": 3,
    "corners": 5,
    "fouls": 17,
    "offsides": 1,
    "yellow_cards": 2,
    "red_cards": 0,
    "saves": 5,
    "expected_goals": 0.33,
    "big_chances_created": 1,
    "big_chances_missed": 1,
    "passes": 418,
    "tackles": 16,
    "interceptions": 6
  },
  "events": [],
  "shot_map": [
    {
      "minute": 3,
      "player_name": "Idrissa Toure",
      "team_id": "6479",
      "x": 101.8706896554,
      "y": 23.2285350362,
      "is_on_target": false,
      "expected_goals": 0.030681870877742767,
      "shot_type": "RightFoot",
      "is_goal": false,
      "is_blocked": false
    },
    {
      "minute": 10,
      "player_name": "M'Bala Nzola",
      "team_id": "6479",
      "x": 78.5432038848,
      "y": 30.95,
      "is_on_target": true,
      "expected_goals": 0.025134749710559845,
      "shot_type": "LeftFoot",
      "is_goal": false,
      "is_blocked": false
    },
    {
      "minute": 14,
      "player_name": "Franco Vázquez",
      "team_id": "7801",
      "x": 87.1044117644,
      "y": 35.29625000000001,
      "is_on_target": false,
      "expected_goals": 0.11704352498054504,
      "shot_type": "LeftFoot",
      "is_goal": false,
      "is_blocked": false
    },
    {
      "minute": 15,
      "player_name": "Franco Vázquez",
      "team_id": "7801",
      "x": 100.25862069,
      "y": 22.387770704599998,
      "is_on_target": false,
      "expected_goals": 0.036451272666454315,
      "shot_type": "LeftFoot",
      "is_goal": false,
      "is_blocked": false
    },
    {
      "minute": 22,
      "player_name": "Antonio Caracciolo",
      "team_id": "6479",
      "x": 97.7631578942,
      "y": 25.4759375,
      "is_on_target": true,
      "expected_goals": 0.02452028915286064,
      "shot_type": "Header",
      "is_goal": false,
      "is_blocked": false
    },
    {
      "minute": 23,
      "player_name": "Idrissa Toure",
      "team_id": "6479",
      "x": 103.103448276,
      "y": 27.782619046999997,
      "is_on_target": false,
      "expected_goals": 0.16112308204174042,
      "shot_type": "Header",
      "is_goal": false,
      "is_blocked": false
    },
    {
      "minute": 24,
      "player_name": "Ebenezer Akinsanmiro",
      "team_id": "6479",
      "x": 78.8810679624,
      "y": 31.941249999999997,
      "is_on_target": true,
      "expected_goals": 0.025308240205049515,
      "shot_type": "RightFoot",
      "is_goal": false,
      "is_blocked": false
    },
    {
      "minute": 33,
      "player_name": "Jamie Vardy",
      "team_id": "7801",
      "x": 91.4,
      "y": 30.568749999999998,
      "is_on_target": true,
      "expected_goals": 0.06920058280229568,
      "shot_type": "RightFoot",
      "is_goal": false,
      "is_blocked": false
    },
    {
      "minute": 33,
      "player_name": "Jari Vandeputte",
      "team_id": "7801",
      "x": 87.85588235280001,
      "y": 32.3225,
      "is_on_target": true,
      "expected_goals": 0.06706947088241577,
      "shot_type": "RightFoot",
      "is_goal": false,
      "is_blocked": false
    },
    {
      "minute": 36,
      "player_name": "Franco Vázquez",
      "team_id": "7801",
      "x": 91.4,
      "y": 43.3701910778,
      "is_on_target": false,
      "expected_goals": 0.046660151332616806,
      "shot_type": "RightFoot",
      "is_goal": false,
      "is_blocked": false
    },
    {
      "minute": 43,
      "player_name": "Mikayil Faye",
      "team_id": "7801",
      "x": 87.85588235280001,
      "y": 45.4721019068,
      "is_on_target": true,
      "expected_goals": 0.011285455897450447,
      "shot_type": "RightFoot",
      "is_goal": false,
      "is_blocked": false
    },
    {
      "minute": 45,
      "player_name": "Isak Vural",
      "team_id": "6479",
      "x": 94.7719298231,
      "y": 38.452380954,
      "is_on_target": false,
      "expected_goals": 0.041378241032361984,
      "shot_type": "Header",
      "is_goal": false,
      "is_blocked": false
    },
    {
      "minute": 51,
      "player_name": "Stefano Moreo",
      "team_id": "6479",
      "x": 100.1637931038,
      "y": 44.1408917151,
      "is_on_target": false,
      "expected_goals": 0.023884600028395653,
      "shot_type": "RightFoot",
      "is_goal": false,
      "is_blocked": false
    },
    {
      "minute": 53,
      "player_name": "M'Bala Nzola",
      "team_id": "6479",
      "x": 92.1,
      "y": 49.956178342,
      "is_on_target": false,
      "expected_goals": 0.015535630285739899,
      "shot_type": "LeftFoot",
      "is_goal": false,
      "is_blocked": false
    },
    {
      "minute": 59,
      "player_name": "M'Bala Nzola",
      "team_id": "6479",
      "x": 100.44827586240001,
      "y": 16.0820382176,
      "is_on_target": true,
      "expected_goals": 0.00863343384116888,
      "shot_type": "RightFoot",
      "is_goal": false,
      "is_blocked": false
    },
    {
      "minute": 60,
      "player_name": "Antonio Caracciolo",
      "team_id": "6479",
      "x": 94.0,
      "y": 38.200238096999996,
      "is_on_target": true,
      "expected_goals": 0.023147955536842346,
      "shot_type": "Header",
      "is_goal": false,
      "is_blocked": false
    },
    {
      "minute": 61,
      "player_name": "Franco Vázquez",
      "team_id": "7801",
      "x": 90.5,
      "y": 17.6234394922,
      "is_on_target": false,
      "expected_goals": 0.028656790032982826,
      "shot_type": "LeftFoot",
      "is_goal": false,
      "is_blocked": false
    },
    {
      "minute": 61,
      "player_name": "Tommaso Barbieri",
      "team_id": "7801",
      "x": 100.06896551759999,
      "y": 27.782619046999997,
      "is_on_target": false,
      "expected_goals": 0.29404735565185547,
      "shot_type": "RightFoot",
      "is_goal": false,
      "is_blocked": false
    },
    {
      "minute": 62,
      "player_name": "Franco Vázquez",
      "team_id": "7801",
      "x": 99.59482758659999,
      "y": 23.9992356735,
      "is_on_target": true,
      "expected_goals": 0.015020926482975483,
      "shot_type": "Header",
      "is_goal": false,
      "is_blocked": false
    },
    {
      "minute": 68,
      "player_name": "Warren Bondo",
      "team_id": "7801",
      "x": 86.24558823480001,
      "y": 34.0,
      "is_on_target": false,
      "expected_goals": 0.05401148274540901,
      "shot_type": "RightFoot",
      "is_goal": false,
      "is_blocked": false
    },
    {
      "minute": 70,
      "player_name": "Jamie Vardy",
      "team_id": "7801",
      "x": 90.4,
      "y": 19.3750318497,
      "is_on_target": true,
      "expected_goals": 0.1051042377948761,
      "shot_type": "RightFoot",
      "is_goal": false,
      "is_blocked": false
    },
    {
      "minute": 71,
      "player_name": "Federico Baschirotto",
      "team_id": "7801",
      "x": 98.4385964909,
      "y": 39.545000001,
      "is_on_target": true,
      "expected_goals": 0.05362143740057945,
      "shot_type": "Header",
      "is_goal": false,
      "is_blocked": false
    },
    {
      "minute": 75,
      "player_name": "Idrissa Toure",
      "team_id": "6479",
      "x": 98.3421052628,
      "y": 34.7625,
      "is_on_target": true,
      "expected_goals": 0.22937211394309998,
      "shot_type": "Header",
      "is_goal": true,
      "is_blocked": false
    },
    {
      "minute": 78,
      "player_name": "M'Bala Nzola",
      "team_id": "6479",
      "x": 97.3771929818,
      "y": 31.254999999999995,
      "is_on_target": false,
      "expected_goals": 0.16415724158287048,
      "shot_type": "Header",
      "is_goal": false,
      "is_blocked": false
    },
    {
      "minute": 79,
      "player_name": "Simone Canestrelli",
      "team_id": "6479",
      "x": 100.3534482762,
      "y": 30.267999999999997,
      "is_on_target": false,
      "expected_goals": 0.14426366984844208,
      "shot_type": "RightFoot",
      "is_goal": false,
      "is_blocked": false
    },
    {
      "minute": 87,
      "player_name": "Tommaso Barbieri",
      "team_id": "7801",
      "x": 91.9,
      "y": 42.2928125,
      "is_on_target": true,
      "expected_goals": 0.07632684707641602,
      "shot_type": "RightFoot",
      "is_goal": false,
      "is_blocked": false
    }
  ],
  "player_ratings": {},
  "data_source": "fotmob",
  "collected_at": "2025-12-11T03:37:54.853205+00:00",
  "data_completeness_score": 0.599
}