{
  "match_id": "4803111",
  "fotmob_id": "4803111",
  "home_team": "Fiorentina",
  "away_team": "Bologna",
  "home_score": 2,
  "away_score": 2,
  "status": "finished",
  "home_stats": {
    "possession": 50.0,
    "shots": 4,
    "shots_on_target": 7,
    "corners": 5,
    "fouls": 13,
    "offsides": 5,
    "yellow_cards": 3,
    "red_cards": 0,
    "saves": 1,
    "expected_goals": 2.53,
    "big_chances_created": 6,
    "big_chances_missed": 4,
    "passes": 256,
    "tackles": 10,
    "interceptions": 6
  },
  "away_stats": {
    "possession": 50.0,
    "shots": 2,
    "shots_on_target": 3,
    "corners": 6,
    "fouls": 20,
    "offsides": 3,
    "yellow_cards": 3,
    "red_cards": 1,
    "saves": 4,
    "expected_goals": 1.86,
    "big_chances_created": 2,
    "big_chances_missed": 0,
    "passes": 252,
    "tackles": 12,
    "interceptions": 8
  },
  "events": [],
  "shot_map": [
    {
      "minute": 12,
      "player_name": "Robin Gosens",
      "team_id": "8535",
      "x": 100.9224137934,
      "y": 37.355000000000004,
      "is_on_target": false,
      "expected_goals": 0.16771149635314941,
      "shot_type": "Header",
      "is_goal": false,
      "is_blocked": false
    },
    {
      "minute": 18,
      "player_name": "Juan Miranda",
      "team_id": "9857",
      "x": 73.9257281576,
      "y": 45.6122292954,
      "is_on_target": true,
      "expected_goals": 0.015882330015301704,
      "shot_type": "LeftFoot",
      "is_goal": false,
      "is_blocked": false
    },
    {
      "minute": 25,
      "player_name": "Santiago Castro",
      "team_id": "9857",
      "x": 94.9649122793,
      "y": 39.208809525,
      "is_on_target": true,
      "expected_goals": 0.1299794465303421,
      "shot_type": "RightFoot",
      "is_goal": true,
      "is_blocked": false
    },
    {
      "minute": 30,
      "player_name": "Rolando Mandragora",
      "team_id": "8535",
      "x": 97.0877192975,
      "y": 34.68625,
      "is_on_target": false,
      "expected_goals": 0.06726720184087753,
      "shot_type": "Header",
      "is_goal": false,
      "is_blocked": false
    },
    {
      "minute": 30,
      "player_name": "Luca Ranieri",
      "team_id": "8535",
      "x": 102.53448275880001,
      "y": 30.22,
      "is_on_target": false,
      "expected_goals": 0.5044659972190857,
      "shot_type": "LeftFoot",
      "is_goal": false,
      "is_blocked": false
    },
    {
      "minute": 33,
      "player_name": "Nicolo Cambiaghi",
      "team_id": "9857",
      "x": 91.0,
      "y": 50.166369424900005,
      "is_on_target": false,
      "expected_goals": 0.02996414341032505,
      "shot_type": "RightFoot",
      "is_goal": false,
      "is_blocked": false
    },
    {
      "minute": 40,
      "player_name": "Rolando Mandragora",
      "team_id": "8535",
      "x": 77.3043689336,
      "y": 23.718980896300003,
      "is_on_target": true,
      "expected_goals": 0.03379453346133232,
      "shot_type": "LeftFoot",
      "is_goal": false,
      "is_blocked": false
    },
    {
      "minute": 40,
      "player_name": "Dodo",
      "team_id": "8535",
      "x": 99.50000000040001,
      "y": 23.2985987305,
      "is_on_target": false,
      "expected_goals": 0.08534307032823563,
      "shot_type": "RightFoot",
      "is_goal": false,
      "is_blocked": false
    },
    {
      "minute": 46,
      "player_name": "Moise Kean",
      "team_id": "8535",
      "x": 93.3,
      "y": 25.302500000000002,
      "is_on_target": true,
      "expected_goals": 0.12545844912528992,
      "shot_type": "RightFoot",
      "is_goal": false,
      "is_blocked": false
    },
    {
      "minute": 46,
      "player_name": "Moise Kean",
      "team_id": "8535",
      "x": 100.1637931038,
      "y": 26.516562500000003,
      "is_on_target": true,
      "expected_goals": 0.10644012689590454,
      "shot_type": "RightFoot",
      "is_goal": false,
      "is_blocked": false
    },
    {
      "minute": 52,
      "player_name": "Nicolo Cambiaghi",
      "team_id": "9857",
      "x": 100.06896551759999,
      "y": 32.0175,
      "is_on_target": true,
      "expected_goals": 0.6977715492248535,
      "shot_type": "LeftFoot",
      "is_goal": true,
      "is_blocked": false
    },
    {
      "minute": 58,
      "player_name": "Moise Kean",
      "team_id": "8535",
      "x": 86.24558823480001,
      "y": 29.211428570000002,
      "is_on_target": true,
      "expected_goals": 0.06676509976387024,
      "shot_type": "LeftFoot",
      "is_goal": false,
      "is_blocked": false
    },
    {
      "minute": 60,
      "player_name": "Santiago Castro",
      "team_id": "9857",
      "x": 73.02475728399999,
      "y": 35.143750000000004,
      "is_on_target": true,
      "expected_goals": 0.02695254422724247,
      "shot_type": "RightFoot",
      "is_goal": false,
      "is_blocked": false
    },
    {
      "minute": 65,
      "player_name": "Abdelhamid Sabiri",
      "team_id": "8535",
      "x": 75.6150485456,
      "y": 28.454999999,
      "is_on_target": false,
      "expected_goals": 0.01244001928716898,
      "shot_type": "RightFoot",
      "is_goal": false,
      "is_blocked": false
    },
    {
      "minute": 66,
      "player_name": "Giovanni Fabbian",
      "team_id": "9857",
      "x": 98.0526315785,
      "y": 31.559999999999995,
      "is_on_target": false,
      "expected_goals": 0.11752801388502121,
      "shot_type": "Header",
      "is_goal": false,
      "is_blocked": false
    },
    {
      "minute": 72,
      "player_name": "Edin Dzeko",
      "team_id": "8535",
      "x": 96.3157894727,
      "y": 41.9459375,
      "is_on_target": true,
      "expected_goals": 0.019224034622311592,
      "shot_type": "Header",
      "is_goal": false,
      "is_blocked": false
    },
    {
      "minute": 72,
      "player_name": "Moise Kean",
      "team_id": "8535",
      "x": 100.44827586240001,
      "y": 34.838750000000005,
      "is_on_target": true,
      "expected_goals": 0.28268522024154663,
      "shot_type": "RightFoot",
      "is_goal": false,
      "is_blocked": false
    },
    {
      "minute": 73,
      "player_name": "Albert Gudmundsson",
      "team_id": "8535",
      "x": 94.0,
      "y": 34.0,
      "is_on_target": true,
      "expected_goals": 0.7884,
      "shot_type": "RightFoot",
      "is_goal": true,
      "is_blocked": false
    },
    {
      "minute": 80,
      "player_name": "Marin Pongracic",
      "team_id": "8535",
      "x": 94.7719298231,
      "y": 31.636249999999997,
      "is_on_target": false,
      "expected_goals": 0.05068973824381828,
      "shot_type": "Header",
      "is_goal": false,
      "is_blocked": false
    },
    {
      "minute": 80,
      "player_name": "Albert Gudmundsson",
      "team_id": "8535",
      "x": 99.8793103452,
      "y": 46.0326114612,
      "is_on_target": true,
      "expected_goals": 0.02381886914372444,
      "shot_type": "LeftFoot",
      "is_goal": false,
      "is_blocked": false
    },
    {
      "minute": 83,
      "player_name": "Luca Ranieri",
      "team_id": "8535",
      "x": 81.24611650560001,
      "y": 43.5103184664,
      "is_on_target": true,
      "expected_goals": 0.011906160973012447,
      "shot_type": "LeftFoot",
      "is_goal": false,
      "is_blocked": false
    },
    {
      "minute": 90,
      "player_name": "Moise Kean",
      "team_id": "8535",
      "x": 96.2192982446,
      "y": 37.94809524,
      "is_on_target": true,
      "expected_goals": 0.06727095693349838,
      "shot_type": "RightFoot",
      "is_goal": false,
      "is_blocked": false
    },
    {
      "minute": 90,
      "player_name": "Moise Kean",
      "team_id": "8535",
      "x": 94.0,
      "y": 34.0,
      "is_on_target": true,
      "expected_goals": 0.7884,
      "shot_type": "RightFoot",
      "is_goal": true,
      "is_blocked": false
    },
    {
      "minute": 90,
      "player_name": "Roberto Piccoli",
      "team_id": "8535",
      "x": 95.8333333322,
      "y": 37.72,
      "is_on_target": true,
      "expected_goals": 0.05309412628412247,
      "shot_type": "Header",
      "is_goal": false,
      "is_blocked": false
    },
    {
      "minute": 90,
      "player_name": "Dodo",
      "team_id": "8535",
      "x": 101.681034483,
      "y": 27.614523809,
      "is_on_target": false,
      "expected_goals": 0.48973017930984497,
      "shot_type": "RightFoot",
      "is_goal": false,
      "is_blocked": false
    }
  ],
  "player_ratings": {},
  "data_source": "fotmob",
  "collected_at": "2025-12-11T03:38:13.811630+00:00",
  "data_completeness_score": 0.599
}