{
  "match_id": "4803096",
  "fotmob_id": "4803096",
  "home_team": "Udinese",
  "away_team": "Cagliari",
  "home_score": 1,
  "away_score": 1,
  "status": "finished",
  "home_stats": {
    "possession": 60.0,
    "shots": 8,
    "shots_on_target": 4,
    "corners": 7,
    "fouls": 14,
    "offsides": 0,
    "yellow_cards": 1,
    "red_cards": 0,
    "saves": 2,
    "expected_goals": 2.06,
    "big_chances_created": 7,
    "big_chances_missed": 6,
    "passes": 368,
    "tackles": 14,
    "interceptions": 10
  },
  "away_stats": {
    "possession": 40.0,
    "shots": 3,
    "shots_on_target": 2,
    "corners": 2,
    "fouls": 16,
    "offsides": 0,
    "yellow_cards": 2,
    "red_cards": 0,
    "saves": 3,
    "expected_goals": 0.88,
    "big_chances_created": 1,
    "big_chances_missed": 0,
    "passes": 216,
    "tackles": 20,
    "interceptions": 5
  },
  "events": [],
  "shot_map": [
    {
      "minute": 3,
      "player_name": "Oumar Solet",
      "team_id": "8600",
      "x": 77.529611652,
      "y": 37.732,
      "is_on_target": true,
      "expected_goals": 0.012210611253976822,
      "shot_type": "RightFoot",
      "is_goal": false,
      "is_blocked": false
    },
    {
      "minute": 4,
      "player_name": "Christian Kabasele",
      "team_id": "8600",
      "x": 95.0614035074,
      "y": 30.34,
      "is_on_target": true,
      "expected_goals": 0.048233214765787125,
      "shot_type": "Header",
      "is_goal": false,
      "is_blocked": false
    },
    {
      "minute": 8,
      "player_name": "Nicolo Zaniolo",
      "team_id": "8600",
      "x": 100.44827586240001,
      "y": 47.013503181400004,
      "is_on_target": false,
      "expected_goals": 0.03382287546992302,
      "shot_type": "LeftFoot",
      "is_goal": false,
      "is_blocked": false
    },
    {
      "minute": 23,
      "player_name": "Gennaro Borrelli",
      "team_id": "8529",
      "x": 85.17205882280001,
      "y": 30.797499999999996,
      "is_on_target": true,
      "expected_goals": 0.07420112937688828,
      "shot_type": "RightFoot",
      "is_goal": false,
      "is_blocked": false
    },
    {
      "minute": 25,
      "player_name": "Mattia Felici",
      "team_id": "8529",
      "x": 91.8,
      "y": 52.758726114000005,
      "is_on_target": true,
      "expected_goals": 0.013918430544435978,
      "shot_type": "RightFoot",
      "is_goal": false,
      "is_blocked": false
    },
    {
      "minute": 25,
      "player_name": "Matteo Prati",
      "team_id": "8529",
      "x": 86.5676470584,
      "y": 33.92375,
      "is_on_target": true,
      "expected_goals": 0.12086597084999084,
      "shot_type": "RightFoot",
      "is_goal": false,
      "is_blocked": false
    },
    {
      "minute": 25,
      "player_name": "Gennaro Borrelli",
      "team_id": "8529",
      "x": 97.1842105256,
      "y": 36.5925,
      "is_on_target": true,
      "expected_goals": 0.40612953901290894,
      "shot_type": "RightFoot",
      "is_goal": true,
      "is_blocked": false
    },
    {
      "minute": 28,
      "player_name": "Arthur Atta",
      "team_id": "8600",
      "x": 78.2053398072,
      "y": 29.883809522,
      "is_on_target": true,
      "expected_goals": 0.02203434891998768,
      "shot_type": "RightFoot",
      "is_goal": false,
      "is_blocked": false
    },
    {
      "minute": 28,
      "player_name": "Hassane Kamara",
      "team_id": "8600",
      "x": 101.3965517244,
      "y": 49.1854777047,
      "is_on_target": true,
      "expected_goals": 0.012479976750910282,
      "shot_type": "LeftFoot",
      "is_goal": false,
      "is_blocked": false
    },
    {
      "minute": 36,
      "player_name": "Nicolo Zaniolo",
      "team_id": "8600",
      "x": 79.21893204,
      "y": 25.302500000000002,
      "is_on_target": true,
      "expected_goals": 0.03993320092558861,
      "shot_type": "LeftFoot",
      "is_goal": false,
      "is_blocked": false
    },
    {
      "minute": 36,
      "player_name": "Jakub Piotrowski",
      "team_id": "8600",
      "x": 91.4,
      "y": 39.545000001,
      "is_on_target": true,
      "expected_goals": 0.1273791640996933,
      "shot_type": "LeftFoot",
      "is_goal": false,
      "is_blocked": false
    },
    {
      "minute": 39,
      "player_name": "Arthur Atta",
      "team_id": "8600",
      "x": 92.3,
      "y": 38.116190478,
      "is_on_target": false,
      "expected_goals": 0.1711132675409317,
      "shot_type": "RightFoot",
      "is_goal": false,
      "is_blocked": false
    },
    {
      "minute": 40,
      "player_name": "Arthur Atta",
      "team_id": "8600",
      "x": 102.155172414,
      "y": 38.452380954,
      "is_on_target": false,
      "expected_goals": 0.28874993324279785,
      "shot_type": "Header",
      "is_goal": false,
      "is_blocked": false
    },
    {
      "minute": 41,
      "player_name": "Jakub Piotrowski",
      "team_id": "8600",
      "x": 94.8684210512,
      "y": 36.135000000000005,
      "is_on_target": true,
      "expected_goals": 0.09909369796514511,
      "shot_type": "RightFoot",
      "is_goal": false,
      "is_blocked": false
    },
    {
      "minute": 42,
      "player_name": "Jesper Karlström",
      "team_id": "8600",
      "x": 83.49854368960001,
      "y": 36.135000000000005,
      "is_on_target": false,
      "expected_goals": 0.05585193634033203,
      "shot_type": "RightFoot",
      "is_goal": false,
      "is_blocked": false
    },
    {
      "minute": 43,
      "player_name": "Sebastiano Esposito",
      "team_id": "8529",
      "x": 87.53382352919999,
      "y": 45.6122292954,
      "is_on_target": false,
      "expected_goals": 0.029836321249604225,
      "shot_type": "RightFoot",
      "is_goal": false,
      "is_blocked": false
    },
    {
      "minute": 45,
      "player_name": "Hassane Kamara",
      "team_id": "8600",
      "x": 83.6111650488,
      "y": 36.135000000000005,
      "is_on_target": true,
      "expected_goals": 0.025887692347168922,
      "shot_type": "RightFoot",
      "is_goal": false,
      "is_blocked": false
    },
    {
      "minute": 47,
      "player_name": "Saba Goglichidze",
      "team_id": "8600",
      "x": 101.0172413796,
      "y": 40.30142857199999,
      "is_on_target": false,
      "expected_goals": 0.08643454313278198,
      "shot_type": "RightFoot",
      "is_goal": false,
      "is_blocked": false
    },
    {
      "minute": 50,
      "player_name": "Arthur Atta",
      "team_id": "8600",
      "x": 79.1063106808,
      "y": 36.2875,
      "is_on_target": true,
      "expected_goals": 0.016792967915534973,
      "shot_type": "RightFoot",
      "is_goal": false,
      "is_blocked": false
    },
    {
      "minute": 53,
      "player_name": "Alessandro Di Pardo",
      "team_id": "8529",
      "x": 98.0526315785,
      "y": 32.24625,
      "is_on_target": false,
      "expected_goals": 0.15929530560970306,
      "shot_type": "Header",
      "is_goal": false,
      "is_blocked": false
    },
    {
      "minute": 58,
      "player_name": "Christian Kabasele",
      "team_id": "8600",
      "x": 100.6379310348,
      "y": 35.0675,
      "is_on_target": true,
      "expected_goals": 0.26706889271736145,
      "shot_type": "RightFoot",
      "is_goal": true,
      "is_blocked": false
    },
    {
      "minute": 70,
      "player_name": "Nicolo Zaniolo",
      "team_id": "8600",
      "x": 75.0519417496,
      "y": 21.687133761599995,
      "is_on_target": true,
      "expected_goals": 0.008858589455485344,
      "shot_type": "LeftFoot",
      "is_goal": false,
      "is_blocked": false
    },
    {
      "minute": 74,
      "player_name": "Nicolo Zaniolo",
      "team_id": "8600",
      "x": 98.0526315785,
      "y": 36.2875,
      "is_on_target": false,
      "expected_goals": 0.39052340388298035,
      "shot_type": "RightFoot",
      "is_goal": false,
      "is_blocked": false
    },
    {
      "minute": 75,
      "player_name": "Nicolo Zaniolo",
      "team_id": "8600",
      "x": 86.6749999996,
      "y": 23.859108284899996,
      "is_on_target": true,
      "expected_goals": 0.023860836401581764,
      "shot_type": "LeftFoot",
      "is_goal": false,
      "is_blocked": false
    },
    {
      "minute": 77,
      "player_name": "Michel Ndary Adopo",
      "team_id": "8529",
      "x": 101.1120689658,
      "y": 40.721666666999994,
      "is_on_target": false,
      "expected_goals": 0.08726304769515991,
      "shot_type": "Header",
      "is_goal": false,
      "is_blocked": false
    },
    {
      "minute": 78,
      "player_name": "Vakoun Issouf Bayo",
      "team_id": "8600",
      "x": 102.06034482780001,
      "y": 21.1966879015,
      "is_on_target": false,
      "expected_goals": 0.024036705493927002,
      "shot_type": "RightFoot",
      "is_goal": false,
      "is_blocked": false
    },
    {
      "minute": 80,
      "player_name": "Vakoun Issouf Bayo",
      "team_id": "8600",
      "x": 96.7017543851,
      "y": 37.27875,
      "is_on_target": false,
      "expected_goals": 0.0628681629896164,
      "shot_type": "Header",
      "is_goal": false,
      "is_blocked": false
    },
    {
      "minute": 81,
      "player_name": "Zito Luvumbo",
      "team_id": "8529",
      "x": 97.3771929818,
      "y": 23.2285350362,
      "is_on_target": false,
      "expected_goals": 0.07290200144052505,
      "shot_type": "RightFoot",
      "is_goal": false,
      "is_blocked": false
    },
    {
      "minute": 85,
      "player_name": "Arthur Atta",
      "team_id": "8600",
      "x": 92.0,
      "y": 30.232,
      "is_on_target": true,
      "expected_goals": 0.1042734831571579,
      "shot_type": "RightFoot",
      "is_goal": false,
      "is_blocked": false
    },
    {
      "minute": 90,
      "player_name": "Keinan Davis",
      "team_id": "8600",
      "x": 95.15789473550001,
      "y": 26.774047619,
      "is_on_target": true,
      "expected_goals": 0.4246551990509033,
      "shot_type": "RightFoot",
      "is_goal": false,
      "is_blocked": false
    },
    {
      "minute": 90,
      "player_name": "Vakoun Issouf Bayo",
      "team_id": "8600",
      "x": 101.0172413796,
      "y": 37.50750000000001,
      "is_on_target": false,
      "expected_goals": 0.5839724540710449,
      "shot_type": "RightFoot",
      "is_goal": false,
      "is_blocked": false
    }
  ],
  "player_ratings": {},
  "data_source": "fotmob",
  "collected_at": "2025-12-11T03:38:29.847132+00:00",
  "data_completeness_score": 0.599
}