{
  "match_id": "4803139",
  "fotmob_id": "4803139",
  "home_team": "Bologna",
  "away_team": "Napoli",
  "home_score": 2,
  "away_score": 0,
  "status": "finished",
  "home_stats": {
    "possession": 41.0,
    "shots": 5,
    "shots_on_target": 4,
    "corners": 5,
    "fouls": 14,
    "offsides": 0,
    "yellow_cards": 1,
    "red_cards": 0,
    "saves": 1,
    "expected_goals": 1.17,
    "big_chances_created": 3,
    "big_chances_missed": 1,
    "passes": 297,
    "tackles": 14,
    "interceptions": 7
  },
  "away_stats": {
    "possession": 59.0,
    "shots": 3,
    "shots_on_target": 1,
    "corners": 4,
    "fouls": 15,
    "offsides": 0,
    "yellow_cards": 3,
    "red_cards": 0,
    "saves": 2,
    "expected_goals": 0.1,
    "big_chances_created": 0,
    "big_chances_missed": 0,
    "passes": 467,
    "tackles": 9,
    "interceptions": 4
  },
  "events": [],
  "shot_map": [
    {
      "minute": 17,
      "player_name": "Rasmus Højlund",
      "team_id": "9875",
      "x": 84.62475728160001,
      "y": 40.30142857199999,
      "is_on_target": true,
      "expected_goals": 0.049625735729932785,
      "shot_type": "LeftFoot",
      "is_goal": false,
      "is_blocked": false
    },
    {
      "minute": 19,
      "player_name": "Eljif Elmas",
      "team_id": "9875",
      "x": 84.3995145632,
      "y": 45.6122292954,
      "is_on_target": true,
      "expected_goals": 0.03963693603873253,
      "shot_type": "RightFoot",
      "is_goal": false,
      "is_blocked": false
    },
    {
      "minute": 20,
      "player_name": "Jonathan Rowe",
      "team_id": "9857",
      "x": 76.6286407784,
      "y": 40.385476190999995,
      "is_on_target": true,
      "expected_goals": 0.018893519416451454,
      "shot_type": "RightFoot",
      "is_goal": false,
      "is_blocked": false
    },
    {
      "minute": 22,
      "player_name": "Jhon Lucumi",
      "team_id": "9857",
      "x": 99.3070175438,
      "y": 30.797499999999996,
      "is_on_target": false,
      "expected_goals": 0.20744533836841583,
      "shot_type": "Header",
      "is_goal": false,
      "is_blocked": false
    },
    {
      "minute": 32,
      "player_name": "Jonathan Rowe",
      "team_id": "9857",
      "x": 76.0655339824,
      "y": 37.684,
      "is_on_target": true,
      "expected_goals": 0.037136051803827286,
      "shot_type": "RightFoot",
      "is_goal": false,
      "is_blocked": false
    },
    {
      "minute": 35,
      "player_name": "Thijs Dallinga",
      "team_id": "9857",
      "x": 94.675438595,
      "y": 32.6275,
      "is_on_target": false,
      "expected_goals": 0.059593282639980316,
      "shot_type": "Header",
      "is_goal": false,
      "is_blocked": false
    },
    {
      "minute": 45,
      "player_name": "Scott McTominay",
      "team_id": "9875",
      "x": 97.0877192975,
      "y": 33.39,
      "is_on_target": false,
      "expected_goals": 0.07199889421463013,
      "shot_type": "Header",
      "is_goal": false,
      "is_blocked": false
    },
    {
      "minute": 50,
      "player_name": "Thijs Dallinga",
      "team_id": "9857",
      "x": 101.3965517244,
      "y": 39.208809525,
      "is_on_target": true,
      "expected_goals": 0.14431534707546234,
      "shot_type": "RightFoot",
      "is_goal": true,
      "is_blocked": false
    },
    {
      "minute": 58,
      "player_name": "Riccardo Orsolini",
      "team_id": "9857",
      "x": 96.50877192889999,
      "y": 15.101146497399998,
      "is_on_target": true,
      "expected_goals": 0.00700793182477355,
      "shot_type": "LeftFoot",
      "is_goal": false,
      "is_blocked": false
    },
    {
      "minute": 66,
      "player_name": "Jhon Lucumi",
      "team_id": "9857",
      "x": 99.59482758659999,
      "y": 32.551249999999996,
      "is_on_target": true,
      "expected_goals": 0.3445984423160553,
      "shot_type": "Header",
      "is_goal": true,
      "is_blocked": false
    },
    {
      "minute": 69,
      "player_name": "Scott McTominay",
      "team_id": "9875",
      "x": 83.8364077672,
      "y": 20.3559235699,
      "is_on_target": true,
      "expected_goals": 0.04910822957754135,
      "shot_type": "RightFoot",
      "is_goal": false,
      "is_blocked": false
    },
    {
      "minute": 73,
      "player_name": "Nicolo Cambiaghi",
      "team_id": "9857",
      "x": 80.4577669912,
      "y": 51.6377070052,
      "is_on_target": true,
      "expected_goals": 0.014652601443231106,
      "shot_type": "RightFoot",
      "is_goal": false,
      "is_blocked": false
    },
    {
      "minute": 73,
      "player_name": "Federico Bernardeschi",
      "team_id": "9857",
      "x": 82.7101941752,
      "y": 27.446428571,
      "is_on_target": false,
      "expected_goals": 0.01948329247534275,
      "shot_type": "LeftFoot",
      "is_goal": false,
      "is_blocked": false
    },
    {
      "minute": 85,
      "player_name": "Juan Miranda",
      "team_id": "9857",
      "x": 102.4396551726,
      "y": 45.2619108239,
      "is_on_target": true,
      "expected_goals": 0.03390411660075188,
      "shot_type": "LeftFoot",
      "is_goal": false,
      "is_blocked": false
    },
    {
      "minute": 90,
      "player_name": "Federico Bernardeschi",
      "team_id": "9857",
      "x": 86.4602941172,
      "y": 41.057857143,
      "is_on_target": false,
      "expected_goals": 0.03357050195336342,
      "shot_type": "RightFoot",
      "is_goal": false,
      "is_blocked": false
    }
  ],
  "player_ratings": {},
  "data_source": "fotmob",
  "collected_at": "2025-12-11T03:38:07.861184+00:00",
  "data_completeness_score": 0.599
}