{
  "match_id": "4803117",
  "fotmob_id": "4803117",
  "home_team": "Torino",
  "away_team": "Genoa",
  "home_score": 2,
  "away_score": 1,
  "status": "finished",
  "home_stats": {
    "possession": 59.0,
    "shots": 4,
    "shots_on_target": 6,
    "corners": 9,
    "fouls": 14,
    "offsides": 1,
    "yellow_cards": 2,
    "red_cards": 0,
    "saves": 2,
    "expected_goals": 1.94,
    "big_chances_created": 3,
    "big_chances_missed": 2,
    "passes": 392,
    "tackles": 16,
    "interceptions": 3
  },
  "away_stats": {
    "possession": 41.0,
    "shots": 3,
    "shots_on_target": 3,
    "corners": 1,
    "fouls": 9,
    "offsides": 0,
    "yellow_cards": 2,
    "red_cards": 0,
    "saves": 5,
    "expected_goals": 0.81,
    "big_chances_created": 4,
    "big_chances_missed": 3,
    "passes": 269,
    "tackles": 14,
    "interceptions": 4
  },
  "events": [],
  "shot_map": [
    {
      "minute": 7,
      "player_name": "Morten Thorsby",
      "team_id": "10233",
      "x": 100.06896551759999,
      "y": 36.135000000000005,
      "is_on_target": true,
      "expected_goals": 0.6122220754623413,
      "shot_type": "RightFoot",
      "is_goal": true,
      "is_blocked": false
    },
    {
      "minute": 18,
      "player_name": "Ruslan Malinovsky",
      "team_id": "10233",
      "x": 74.3762135944,
      "y": 15.3814012746,
      "is_on_target": false,
      "expected_goals": 0.026093825697898865,
      "shot_type": "LeftFoot",
      "is_goal": false,
      "is_blocked": false
    },
    {
      "minute": 20,
      "player_name": "Morten Thorsby",
      "team_id": "10233",
      "x": 94.09649122639999,
      "y": 37.732,
      "is_on_target": false,
      "expected_goals": 0.03291018679738045,
      "shot_type": "Header",
      "is_goal": false,
      "is_blocked": false
    },
    {
      "minute": 20,
      "player_name": "Jeff Ekhator",
      "team_id": "10233",
      "x": 92.2,
      "y": 31.7125,
      "is_on_target": false,
      "expected_goals": 0.2956570088863373,
      "shot_type": "RightFoot",
      "is_goal": false,
      "is_blocked": false
    },
    {
      "minute": 39,
      "player_name": "Kristjan Asllani",
      "team_id": "9804",
      "x": 85.81617647,
      "y": 38.620476192,
      "is_on_target": true,
      "expected_goals": 0.11024519801139832,
      "shot_type": "RightFoot",
      "is_goal": false,
      "is_blocked": false
    },
    {
      "minute": 39,
      "player_name": "Guillermo Maripan",
      "team_id": "9804",
      "x": 101.8706896554,
      "y": 39.040714287,
      "is_on_target": true,
      "expected_goals": 0.12380506098270416,
      "shot_type": "LeftFoot",
      "is_goal": false,
      "is_blocked": false
    },
    {
      "minute": 45,
      "player_name": "Saul Coco",
      "team_id": "9804",
      "x": 94.7719298231,
      "y": 30.05190476,
      "is_on_target": false,
      "expected_goals": 0.03194989636540413,
      "shot_type": "Header",
      "is_goal": false,
      "is_blocked": false
    },
    {
      "minute": 56,
      "player_name": "Jeff Ekhator",
      "team_id": "10233",
      "x": 85.6014705876,
      "y": 29.715714284,
      "is_on_target": true,
      "expected_goals": 0.06698252260684967,
      "shot_type": "RightFoot",
      "is_goal": false,
      "is_blocked": false
    },
    {
      "minute": 58,
      "player_name": "Guillermo Maripan",
      "team_id": "9804",
      "x": 96.50877192889999,
      "y": 36.2875,
      "is_on_target": true,
      "expected_goals": 0.07738179713487625,
      "shot_type": "Header",
      "is_goal": false,
      "is_blocked": false
    },
    {
      "minute": 59,
      "player_name": "Giovanni Simeone",
      "team_id": "9804",
      "x": 90.5,
      "y": 30.797499999999996,
      "is_on_target": false,
      "expected_goals": 0.06897356361150742,
      "shot_type": "RightFoot",
      "is_goal": false,
      "is_blocked": false
    },
    {
      "minute": 68,
      "player_name": "Morten Thorsby",
      "team_id": "10233",
      "x": 92.7,
      "y": 42.813125,
      "is_on_target": true,
      "expected_goals": 0.09128206223249435,
      "shot_type": "RightFoot",
      "is_goal": false,
      "is_blocked": false
    },
    {
      "minute": 71,
      "player_name": "Valentino Lazaro",
      "team_id": "9804",
      "x": 90.4,
      "y": 31.026249999999997,
      "is_on_target": true,
      "expected_goals": 0.06130140647292137,
      "shot_type": "RightFoot",
      "is_goal": false,
      "is_blocked": false
    },
    {
      "minute": 71,
      "player_name": "Cyril Ngonge",
      "team_id": "9804",
      "x": 101.206896552,
      "y": 37.684,
      "is_on_target": true,
      "expected_goals": 0.3692132532596588,
      "shot_type": "Header",
      "is_goal": false,
      "is_blocked": false
    },
    {
      "minute": 73,
      "player_name": "Ruslan Malinovsky",
      "team_id": "10233",
      "x": 92.5,
      "y": 44.2810191037,
      "is_on_target": false,
      "expected_goals": 0.06254300475120544,
      "shot_type": "RightFoot",
      "is_goal": false,
      "is_blocked": false
    },
    {
      "minute": 75,
      "player_name": "Cyril Ngonge",
      "team_id": "9804",
      "x": 83.8364077672,
      "y": 23.9992356735,
      "is_on_target": true,
      "expected_goals": 0.02139587700366974,
      "shot_type": "LeftFoot",
      "is_goal": false,
      "is_blocked": false
    },
    {
      "minute": 81,
      "player_name": "Saul Coco",
      "team_id": "9804",
      "x": 75.1645631088,
      "y": 33.00875,
      "is_on_target": true,
      "expected_goals": 0.03511137515306473,
      "shot_type": "RightFoot",
      "is_goal": false,
      "is_blocked": false
    },
    {
      "minute": 84,
      "player_name": "Cesare Casadei",
      "team_id": "9804",
      "x": 91.3,
      "y": 32.70374999999999,
      "is_on_target": true,
      "expected_goals": 0.020246071740984917,
      "shot_type": "Header",
      "is_goal": false,
      "is_blocked": false
    },
    {
      "minute": 84,
      "player_name": "Cesare Casadei",
      "team_id": "9804",
      "x": 100.9224137934,
      "y": 32.70374999999999,
      "is_on_target": false,
      "expected_goals": 0.28027355670928955,
      "shot_type": "Header",
      "is_goal": false,
      "is_blocked": false
    },
    {
      "minute": 86,
      "player_name": "Duvan Zapata",
      "team_id": "9804",
      "x": 86.0308823524,
      "y": 44.7014012695,
      "is_on_target": true,
      "expected_goals": 0.022864747792482376,
      "shot_type": "RightFoot",
      "is_goal": false,
      "is_blocked": false
    },
    {
      "minute": 89,
      "player_name": "Lorenzo Colombo",
      "team_id": "10233",
      "x": 95.35087719170001,
      "y": 27.110238095,
      "is_on_target": false,
      "expected_goals": 0.081047922372818,
      "shot_type": "RightFoot",
      "is_goal": false,
      "is_blocked": false
    },
    {
      "minute": 90,
      "player_name": "Guillermo Maripan",
      "team_id": "9804",
      "x": 96.79824561320001,
      "y": 35.60125,
      "is_on_target": true,
      "expected_goals": 0.12277171015739441,
      "shot_type": "RightFoot",
      "is_goal": true,
      "is_blocked": false
    },
    {
      "minute": 90,
      "player_name": "Caleb Ekuban",
      "team_id": "10233",
      "x": 96.605263157,
      "y": 36.440000000000005,
      "is_on_target": true,
      "expected_goals": 0.22762617468833923,
      "shot_type": "Header",
      "is_goal": false,
      "is_blocked": false
    },
    {
      "minute": 90,
      "player_name": "Mikael Egill Ellertsson",
      "team_id": "10233",
      "x": 76.5160194192,
      "y": 34.68625,
      "is_on_target": true,
      "expected_goals": 0.01398239005357027,
      "shot_type": "LeftFoot",
      "is_goal": false,
      "is_blocked": false
    },
    {
      "minute": 90,
      "player_name": "Maxwel Cornet",
      "team_id": "10233",
      "x": 98.0526315785,
      "y": 32.17,
      "is_on_target": true,
      "expected_goals": 0.5571635961532593,
      "shot_type": "LeftFoot",
      "is_goal": false,
      "is_blocked": false
    }
  ],
  "player_ratings": {},
  "data_source": "fotmob",
  "collected_at": "2025-12-11T03:38:14.492999+00:00",
  "data_completeness_score": 0.599
}