{
  "Austin Fc": "Austin FC",
  "Cf Montreal": "CF Montreal",
  "Charlotte Fc": "Charlotte FC",
  "Chicago Fire Fc": "Chicago Fire FC",
  "Dc United": "DC United",
  "Fc Cincinnati": "FC Cincinnati",
  "Fc Dallas": "FC Dallas",
  "Chengdu Rongcheng": "Chengdu Rongcheng FC",
  "Henan FC": "Henan Songshan Longmen",
  "Henan Fc": "Henan Songshan Longmen",
  "Henan Songshan Longmen": "Henan FC",
  "Houston Dynamo Fc": "Houston Dynamo FC",
  "Inter Miami Cf": "Inter Miami CF",
  "La Galaxy": "LA Galaxy",
  "Ath Bilbao": "Athletic Club",
  "Athletic Bilbao": "Athletic Club",
  "Los Angeles Fc": "Los Angeles FC",
  "Nashville Sc": "Nashville SC",
  "New York City Fc": "New York City FC",
  "New York Red Bulls": "Red Bull New York",
  "New York Red Bulls Fc": "Red Bull New York",
  "Bournemouth": "AFC Bournemouth",
  "Brighton": "Brighton & Hove Albion",
  "Leeds": "Leeds United",
  "Newcastle Utd": "Newcastle United",
  "Nottingham": "Nottingham Forest",
  "Tottenham": "Tottenham Hotspur",
  "West Ham": "West Ham United",
  "Wolves": "Wolverhampton Wanderers",
  "San Diego Fc": "San Diego FC",
  "Seattle Sounders Fc": "Seattle Sounders FC",
  "Chengdu Rongcheng FC": "Chengdu Rongcheng",
  "Chengdu Rongcheng Fc": "Chengdu Rongcheng",
  "Shenzhen Peng City": "Shenzhen Xinpengcheng",
  "Shenzhen Xinpengcheng": "Shenzhen Peng City",
  "Shanghai SIPG": "Shanghai Port",
  "Shanghai Sipg": "Shanghai Port",
  "Shandong Luneng": "Shandong Taishan",
  "Shandong Luneng Taishan": "Shandong Taishan",
  "Bragantino": "Red Bull Bragantino",
  "Rj Santos": "Santos FC",
  "Sporting Kansas": "Sporting Kansas City",
  "St Louis City": "St. Louis City",
  "Afs": "AVS Futebol SAD",
  "Avs": "AVS Futebol SAD",
  "Entella": "Virtus Entella",
  "Heerenveen": "SC Heerenveen",
  "Groningen": "FC Groningen",
  "Utrecht": "FC Utrecht",
  "Nijmegen": "NEC Nijmegen",
  "Twente": "FC Twente",
  "Zwolle": "PEC Zwolle",
  "Sittard": "Fortuna Sittard",
  "G A Eagles": "Go Ahead Eagles",
  "Ga Eagles": "Go Ahead Eagles",
  "PSV": "PSV Eindhoven",
  "Atl Madrid": "Atletico Madrid",
  "Getafe": "Getafe CF",
  "Leganes": "CD Leganes",
  "Mallorca": "RCD Mallorca",
  "Sociedad": "Real Sociedad",
  "Villarreal": "Villarreal CF",
  "Inter": "Inter Milan",
  "Juve": "Juventus",
  "Lecce": "US Lecce",
  "Parma": "Parma Calcio 1913",
  "Torino": "Torino FC",
  "Pafos": "Pafos FC",
  "Qarabag Agdam": "Qarabag FK",
  "Bodo Glimt": "Bodø/Glimt",
  "Crvena Zvezda": "FK Crvena Zvezda",
  "Midtjylland": "FC Midtjylland",
  "Ludogorets": "Ludogorets Razgrad",
  "Din Zagreb": "Dinamo Zagreb",
  "Plzen": "Viktoria Plzen",
  "Celje": "NK Celje",
  "Noah": "FC Noah",
  "Zrinjski": "Zrinjski Mostar",
  "Jagiellonia": "Jagiellonia Bialystok",
  "Shakhtar": "Shakhtar Donetsk",
  "Shkendija Tetovo": "KF Shkendija",
  "Omonia": "Omonia Nicosia",
  "Hamrun": "Hamrun Spartans",
  "Rapid Vienna": "Rapid Wien",
  "Legia": "Legia Warszawa",
  "Ac Milan": "Milan",
  "As Roma": "Roma",
  "Cf Real Oviedo": "Real Oviedo",
  "Shimizu S Pulse": "Shimizu S-Pulse",
  "Yokohama F Marinos": "Yokohama F.Marinos",
  "Toronto Fc": "Toronto FC",
  "Tianjin Teda": "Tianjin Jinmen Tiger"
}
