{
  "schema_version": "1.0",
  "phase": "FOTMOB-RAW-JSON-LONG-RUN-COLLECTOR-REGISTRY-SEED-DRY-RUN",
  "description": "Registry-like seed plan for football calendar target registry. Metadata only. No raw JSON. No live FotMob IDs. All source_match_id values are synthetic/fixture-only.",
  "generated_at": "2026-06-04T00:00:00Z",

  "teams": [
    {
      "fixture_id": "team-mun-01",
      "source": "fotmob",
      "source_team_id": "fixture-mun-01",
      "team_name": "Manchester United",
      "team_type": "club",
      "country": "England",
      "gender": "men",
      "active": true
    },
    {
      "fixture_id": "team-liv-01",
      "source": "fotmob",
      "source_team_id": "fixture-liv-01",
      "team_name": "Liverpool",
      "team_type": "club",
      "country": "England",
      "gender": "men",
      "active": true
    },
    {
      "fixture_id": "team-che-01",
      "source": "fotmob",
      "source_team_id": "fixture-che-01",
      "team_name": "Chelsea",
      "team_type": "club",
      "country": "England",
      "gender": "men",
      "active": true
    },
    {
      "fixture_id": "team-new-01",
      "source": "fotmob",
      "source_team_id": "fixture-new-01",
      "team_name": "Newcastle United",
      "team_type": "club",
      "country": "England",
      "gender": "men",
      "active": true
    },
    {
      "fixture_id": "team-rom-01",
      "source": "fotmob",
      "source_team_id": "fixture-rom-01",
      "team_name": "AS Roma",
      "team_type": "club",
      "country": "Italy",
      "gender": "men",
      "active": true
    },
    {
      "fixture_id": "team-tot-01",
      "source": "fotmob",
      "source_team_id": "fixture-tot-01",
      "team_name": "Tottenham Hotspur",
      "team_type": "club",
      "country": "England",
      "gender": "men",
      "active": true
    },
    {
      "fixture_id": "team-eve-01",
      "source": "fotmob",
      "source_team_id": "fixture-eve-01",
      "team_name": "Everton",
      "team_type": "club",
      "country": "England",
      "gender": "men",
      "active": true
    },
    {
      "fixture_id": "team-eng-01",
      "source": "fotmob",
      "source_team_id": "fixture-eng-01",
      "team_name": "England",
      "team_type": "national",
      "country": "England",
      "gender": "men",
      "active": true
    },
    {
      "fixture_id": "team-pol-01",
      "source": "fotmob",
      "source_team_id": "fixture-pol-01",
      "team_name": "Poland",
      "team_type": "national",
      "country": "Poland",
      "gender": "men",
      "active": true
    },
    {
      "fixture_id": "team-ger-01",
      "source": "fotmob",
      "source_team_id": "fixture-ger-01",
      "team_name": "Germany",
      "team_type": "national",
      "country": "Germany",
      "gender": "men",
      "active": true
    },
    {
      "fixture_id": "team-bra-01",
      "source": "fotmob",
      "source_team_id": "fixture-bra-01",
      "team_name": "Brazil",
      "team_type": "national",
      "country": "Brazil",
      "gender": "men",
      "active": true
    },
    {
      "fixture_id": "team-ita-01",
      "source": "fotmob",
      "source_team_id": "fixture-ita-01",
      "team_name": "Italy",
      "team_type": "national",
      "country": "Italy",
      "gender": "men",
      "active": true
    },
    {
      "fixture_id": "team-kas-01",
      "source": "fotmob",
      "source_team_id": "fixture-kas-01",
      "team_name": "Kashima Antlers",
      "team_type": "club",
      "country": "Japan",
      "gender": "men",
      "active": true
    },
    {
      "fixture_id": "team-yok-01",
      "source": "fotmob",
      "source_team_id": "fixture-yok-01",
      "team_name": "Yokohama F. Marinos",
      "team_type": "club",
      "country": "Japan",
      "gender": "men",
      "active": true
    },
    {
      "fixture_id": "team-ura-01",
      "source": "fotmob",
      "source_team_id": "fixture-ura-01",
      "team_name": "Urawa Red Diamonds",
      "team_type": "club",
      "country": "Japan",
      "gender": "men",
      "active": true
    },
    {
      "fixture_id": "team-lee-01",
      "source": "fotmob",
      "source_team_id": "fixture-lee-01",
      "team_name": "Leeds United",
      "team_type": "club",
      "country": "England",
      "gender": "men",
      "active": true
    },
    {
      "fixture_id": "team-sun-01",
      "source": "fotmob",
      "source_team_id": "fixture-sun-01",
      "team_name": "Sunderland",
      "team_type": "club",
      "country": "England",
      "gender": "men",
      "active": true
    },
    {
      "fixture_id": "team-shw-01",
      "source": "fotmob",
      "source_team_id": "fixture-shw-01",
      "team_name": "Sheffield Wednesday",
      "team_type": "club",
      "country": "England",
      "gender": "men",
      "active": true
    }
  ],

  "competitions": [
    {
      "fixture_id": "comp-epl",
      "source": "fotmob",
      "source_competition_id": "fixture-comp-epl",
      "competition_name": "Premier League",
      "competition_type": "league",
      "country": "England",
      "confederation": "UEFA",
      "tier": 0,
      "active": true
    },
    {
      "fixture_id": "comp-facup",
      "source": "fotmob",
      "source_competition_id": "fixture-comp-facup",
      "competition_name": "FA Cup",
      "competition_type": "domestic_cup",
      "country": "England",
      "confederation": "UEFA",
      "tier": 0,
      "active": true
    },
    {
      "fixture_id": "comp-eflcup",
      "source": "fotmob",
      "source_competition_id": "fixture-comp-eflcup",
      "competition_name": "EFL Cup",
      "competition_type": "domestic_cup",
      "country": "England",
      "confederation": "UEFA",
      "tier": 0,
      "active": true
    },
    {
      "fixture_id": "comp-uel",
      "source": "fotmob",
      "source_competition_id": "fixture-comp-uel",
      "competition_name": "UEFA Europa League",
      "competition_type": "continental_club",
      "country": null,
      "confederation": "UEFA",
      "tier": 0,
      "active": true
    },
    {
      "fixture_id": "comp-wcq",
      "source": "fotmob",
      "source_competition_id": "fixture-comp-wcq",
      "competition_name": "FIFA World Cup Qualifier",
      "competition_type": "international_qualifier",
      "country": null,
      "confederation": "UEFA",
      "tier": 0,
      "active": true
    },
    {
      "fixture_id": "comp-unl",
      "source": "fotmob",
      "source_competition_id": "fixture-comp-unl",
      "competition_name": "UEFA Nations League",
      "competition_type": "nations_league",
      "country": null,
      "confederation": "UEFA",
      "tier": 0,
      "active": true
    },
    {
      "fixture_id": "comp-friend",
      "source": "fotmob",
      "source_competition_id": "fixture-comp-friend",
      "competition_name": "International Friendly",
      "competition_type": "friendly",
      "country": null,
      "confederation": null,
      "tier": 2,
      "active": true
    },
    {
      "fixture_id": "comp-j1",
      "source": "fotmob",
      "source_competition_id": "fixture-comp-j1",
      "competition_name": "J1 League",
      "competition_type": "league",
      "country": "Japan",
      "confederation": "AFC",
      "tier": 1,
      "active": true
    },
    {
      "fixture_id": "comp-empcup",
      "source": "fotmob",
      "source_competition_id": "fixture-comp-empcup",
      "competition_name": "Emperor's Cup",
      "competition_type": "domestic_cup",
      "country": "Japan",
      "confederation": "AFC",
      "tier": 1,
      "active": true
    },
    {
      "fixture_id": "comp-champ",
      "source": "fotmob",
      "source_competition_id": "fixture-comp-champ",
      "competition_name": "EFL Championship",
      "competition_type": "league",
      "country": "England",
      "confederation": "UEFA",
      "tier": 1,
      "active": true
    }
  ],

  "competition_editions": [
    {
      "fixture_id": "ed-epl-2526",
      "competition_fixture_id": "comp-epl",
      "season": "2025/2026",
      "edition_name": "Premier League 2025/2026",
      "start_date": "2025-08-15",
      "end_date": "2026-05-24",
      "calendar_type": "season",
      "active": true
    },
    {
      "fixture_id": "ed-facup-2526",
      "competition_fixture_id": "comp-facup",
      "season": "2025/2026",
      "edition_name": "FA Cup 2025/2026",
      "start_date": "2025-11-01",
      "end_date": "2026-05-17",
      "calendar_type": "season",
      "active": true
    },
    {
      "fixture_id": "ed-eflcup-2526",
      "competition_fixture_id": "comp-eflcup",
      "season": "2025/2026",
      "edition_name": "EFL Cup 2025/2026",
      "start_date": "2025-08-12",
      "end_date": "2026-03-01",
      "calendar_type": "season",
      "active": true
    },
    {
      "fixture_id": "ed-uel-2526",
      "competition_fixture_id": "comp-uel",
      "season": "2025/2026",
      "edition_name": "UEFA Europa League 2025/2026",
      "start_date": "2025-09-01",
      "end_date": "2026-05-27",
      "calendar_type": "season",
      "active": true
    },
    {
      "fixture_id": "ed-wcq-2026",
      "competition_fixture_id": "comp-wcq",
      "season": "2026",
      "edition_name": "FIFA World Cup Qualifier 2026",
      "start_date": "2025-03-01",
      "end_date": "2026-03-31",
      "calendar_type": "calendar_year",
      "active": true
    },
    {
      "fixture_id": "ed-unl-2526",
      "competition_fixture_id": "comp-unl",
      "season": "2025/2026",
      "edition_name": "UEFA Nations League 2025/2026",
      "start_date": "2025-09-01",
      "end_date": "2026-06-10",
      "calendar_type": "season",
      "active": true
    },
    {
      "fixture_id": "ed-friend-2526",
      "competition_fixture_id": "comp-friend",
      "season": "2025/2026",
      "edition_name": "International Friendly 2025/2026",
      "start_date": "2025-07-01",
      "end_date": "2026-06-30",
      "calendar_type": "season",
      "active": true
    },
    {
      "fixture_id": "ed-j1-2526",
      "competition_fixture_id": "comp-j1",
      "season": "2025",
      "edition_name": "J1 League 2025",
      "start_date": "2025-02-14",
      "end_date": "2025-12-06",
      "calendar_type": "calendar_year",
      "active": true
    },
    {
      "fixture_id": "ed-empcup-2025",
      "competition_fixture_id": "comp-empcup",
      "season": "2025",
      "edition_name": "Emperor's Cup 2025",
      "start_date": "2025-05-01",
      "end_date": "2025-11-23",
      "calendar_type": "calendar_year",
      "active": true
    },
    {
      "fixture_id": "ed-champ-2526",
      "competition_fixture_id": "comp-champ",
      "season": "2025/2026",
      "edition_name": "EFL Championship 2025/2026",
      "start_date": "2025-08-08",
      "end_date": "2026-05-03",
      "calendar_type": "season",
      "active": true
    }
  ],

  "team_competition_participation": [
    {
      "fixture_id": "tcp-mun-epl-2526",
      "team_fixture_id": "team-mun-01",
      "competition_fixture_id": "comp-epl",
      "edition_fixture_id": "ed-epl-2526",
      "participation_state": "confirmed",
      "qualification_source": "league_table"
    },
    {
      "fixture_id": "tcp-mun-facup-2526",
      "team_fixture_id": "team-mun-01",
      "competition_fixture_id": "comp-facup",
      "edition_fixture_id": "ed-facup-2526",
      "participation_state": "confirmed",
      "qualification_source": "cup_draw"
    },
    {
      "fixture_id": "tcp-mun-eflcup-2526",
      "team_fixture_id": "team-mun-01",
      "competition_fixture_id": "comp-eflcup",
      "edition_fixture_id": "ed-eflcup-2526",
      "participation_state": "confirmed",
      "qualification_source": "cup_draw"
    },
    {
      "fixture_id": "tcp-mun-uel-2526",
      "team_fixture_id": "team-mun-01",
      "competition_fixture_id": "comp-uel",
      "edition_fixture_id": "ed-uel-2526",
      "participation_state": "confirmed",
      "qualification_source": "european_qualification"
    },
    {
      "fixture_id": "tcp-eng-wcq-2026",
      "team_fixture_id": "team-eng-01",
      "competition_fixture_id": "comp-wcq",
      "edition_fixture_id": "ed-wcq-2026",
      "participation_state": "confirmed",
      "qualification_source": "draw"
    },
    {
      "fixture_id": "tcp-eng-unl-2526",
      "team_fixture_id": "team-eng-01",
      "competition_fixture_id": "comp-unl",
      "edition_fixture_id": "ed-unl-2526",
      "participation_state": "confirmed",
      "qualification_source": "draw"
    },
    {
      "fixture_id": "tcp-eng-friend-2526",
      "team_fixture_id": "team-eng-01",
      "competition_fixture_id": "comp-friend",
      "edition_fixture_id": "ed-friend-2526",
      "participation_state": "confirmed",
      "qualification_source": "manual"
    },
    {
      "fixture_id": "tcp-kas-j1-2025",
      "team_fixture_id": "team-kas-01",
      "competition_fixture_id": "comp-j1",
      "edition_fixture_id": "ed-j1-2526",
      "participation_state": "confirmed",
      "qualification_source": "league_table"
    },
    {
      "fixture_id": "tcp-kas-empcup-2025",
      "team_fixture_id": "team-kas-01",
      "competition_fixture_id": "comp-empcup",
      "edition_fixture_id": "ed-empcup-2025",
      "participation_state": "confirmed",
      "qualification_source": "cup_draw"
    },
    {
      "fixture_id": "tcp-lee-champ-2526",
      "team_fixture_id": "team-lee-01",
      "competition_fixture_id": "comp-champ",
      "edition_fixture_id": "ed-champ-2526",
      "participation_state": "confirmed",
      "qualification_source": "league_table"
    },
    {
      "fixture_id": "tcp-lee-facup-2526",
      "team_fixture_id": "team-lee-01",
      "competition_fixture_id": "comp-facup",
      "edition_fixture_id": "ed-facup-2526",
      "participation_state": "confirmed",
      "qualification_source": "cup_draw"
    }
  ],

  "match_targets": [
    {
      "fixture_id": "mt-mun-epl-001",
      "source": "fotmob",
      "source_match_id": "fixture-mun-epl-001",
      "competition_fixture_id": "comp-epl",
      "edition_fixture_id": "ed-epl-2526",
      "match_date": "2026-08-15T14:00:00Z",
      "home_team_fixture_id": "team-mun-01",
      "away_team_fixture_id": "team-liv-01",
      "match_status": "scheduled",
      "target_state": "pending_raw_fetch",
      "priority": 10,
      "discovery_source": "league_schedule",
      "source_url": null,
      "raw_json_status": "missing",
      "last_attempt_at": null,
      "last_success_at": null,
      "attempt_count": 0,
      "last_error_code": null,
      "last_error_message": null
    },
    {
      "fixture_id": "mt-mun-facup-001",
      "source": "fotmob",
      "source_match_id": "fixture-mun-facup-001",
      "competition_fixture_id": "comp-facup",
      "edition_fixture_id": "ed-facup-2526",
      "match_date": "2026-08-22T14:00:00Z",
      "home_team_fixture_id": "team-mun-01",
      "away_team_fixture_id": "team-che-01",
      "match_status": "scheduled",
      "target_state": "pending_raw_fetch",
      "priority": 12,
      "discovery_source": "cup_draw",
      "source_url": null,
      "raw_json_status": "missing",
      "last_attempt_at": null,
      "last_success_at": null,
      "attempt_count": 0,
      "last_error_code": null,
      "last_error_message": null
    },
    {
      "fixture_id": "mt-mun-eflcup-001",
      "source": "fotmob",
      "source_match_id": "fixture-mun-eflcup-001",
      "competition_fixture_id": "comp-eflcup",
      "edition_fixture_id": "ed-eflcup-2526",
      "match_date": "2026-09-12T18:45:00Z",
      "home_team_fixture_id": "team-new-01",
      "away_team_fixture_id": "team-mun-01",
      "match_status": "scheduled",
      "target_state": "pending_raw_fetch",
      "priority": 14,
      "discovery_source": "cup_draw",
      "source_url": null,
      "raw_json_status": "missing",
      "last_attempt_at": null,
      "last_success_at": null,
      "attempt_count": 0,
      "last_error_code": null,
      "last_error_message": null
    },
    {
      "fixture_id": "mt-mun-uel-001",
      "source": "fotmob",
      "source_match_id": "fixture-mun-uel-001",
      "competition_fixture_id": "comp-uel",
      "edition_fixture_id": "ed-uel-2526",
      "match_date": "2026-09-19T19:00:00Z",
      "home_team_fixture_id": "team-mun-01",
      "away_team_fixture_id": "team-rom-01",
      "match_status": "scheduled",
      "target_state": "pending_raw_fetch",
      "priority": 11,
      "discovery_source": "cup_draw",
      "source_url": null,
      "raw_json_status": "missing",
      "last_attempt_at": null,
      "last_success_at": null,
      "attempt_count": 0,
      "last_error_code": null,
      "last_error_message": null
    },
    {
      "fixture_id": "mt-eng-wcq-001",
      "source": "fotmob",
      "source_match_id": "fixture-eng-wcq-001",
      "competition_fixture_id": "comp-wcq",
      "edition_fixture_id": "ed-wcq-2026",
      "match_date": "2026-09-05T18:00:00Z",
      "home_team_fixture_id": "team-eng-01",
      "away_team_fixture_id": "team-pol-01",
      "match_status": "scheduled",
      "target_state": "pending_raw_fetch",
      "priority": 5,
      "discovery_source": "league_schedule",
      "source_url": null,
      "raw_json_status": "missing",
      "last_attempt_at": null,
      "last_success_at": null,
      "attempt_count": 0,
      "last_error_code": null,
      "last_error_message": null
    },
    {
      "fixture_id": "mt-eng-unl-001",
      "source": "fotmob",
      "source_match_id": "fixture-eng-unl-001",
      "competition_fixture_id": "comp-unl",
      "edition_fixture_id": "ed-unl-2526",
      "match_date": "2026-09-09T18:00:00Z",
      "home_team_fixture_id": "team-ger-01",
      "away_team_fixture_id": "team-eng-01",
      "match_status": "scheduled",
      "target_state": "pending_raw_fetch",
      "priority": 8,
      "discovery_source": "league_schedule",
      "source_url": null,
      "raw_json_status": "missing",
      "last_attempt_at": null,
      "last_success_at": null,
      "attempt_count": 0,
      "last_error_code": null,
      "last_error_message": null
    },
    {
      "fixture_id": "mt-eng-friend-001",
      "source": "fotmob",
      "source_match_id": "fixture-eng-friend-001",
      "competition_fixture_id": "comp-friend",
      "edition_fixture_id": "ed-friend-2526",
      "match_date": "2026-10-14T19:00:00Z",
      "home_team_fixture_id": "team-eng-01",
      "away_team_fixture_id": "team-bra-01",
      "match_status": "scheduled",
      "target_state": "pending_raw_fetch",
      "priority": 20,
      "discovery_source": "manual",
      "source_url": null,
      "raw_json_status": "missing",
      "last_attempt_at": null,
      "last_success_at": null,
      "attempt_count": 0,
      "last_error_code": null,
      "last_error_message": null
    },
    {
      "fixture_id": "mt-jpn-j1-001",
      "source": "fotmob",
      "source_match_id": "fixture-jpn-j1-001",
      "competition_fixture_id": "comp-j1",
      "edition_fixture_id": "ed-j1-2526",
      "match_date": "2026-08-16T10:00:00Z",
      "home_team_fixture_id": "team-kas-01",
      "away_team_fixture_id": "team-yok-01",
      "match_status": "scheduled",
      "target_state": "pending_raw_fetch",
      "priority": 15,
      "discovery_source": "league_schedule",
      "source_url": null,
      "raw_json_status": "missing",
      "last_attempt_at": null,
      "last_success_at": null,
      "attempt_count": 0,
      "last_error_code": null,
      "last_error_message": null
    },
    {
      "fixture_id": "mt-jpn-empcup-001",
      "source": "fotmob",
      "source_match_id": "fixture-jpn-empcup-001",
      "competition_fixture_id": "comp-empcup",
      "edition_fixture_id": "ed-empcup-2025",
      "match_date": "2026-09-26T10:00:00Z",
      "home_team_fixture_id": "team-kas-01",
      "away_team_fixture_id": "team-ura-01",
      "match_status": "scheduled",
      "target_state": "pending_raw_fetch",
      "priority": 17,
      "discovery_source": "cup_draw",
      "source_url": null,
      "raw_json_status": "missing",
      "last_attempt_at": null,
      "last_success_at": null,
      "attempt_count": 0,
      "last_error_code": null,
      "last_error_message": null
    },
    {
      "fixture_id": "mt-champ-001",
      "source": "fotmob",
      "source_match_id": "fixture-champ-001",
      "competition_fixture_id": "comp-champ",
      "edition_fixture_id": "ed-champ-2526",
      "match_date": "2026-08-15T14:00:00Z",
      "home_team_fixture_id": "team-lee-01",
      "away_team_fixture_id": "team-sun-01",
      "match_status": "scheduled",
      "target_state": "pending_raw_fetch",
      "priority": 16,
      "discovery_source": "league_schedule",
      "source_url": null,
      "raw_json_status": "missing",
      "last_attempt_at": null,
      "last_success_at": null,
      "attempt_count": 0,
      "last_error_code": null,
      "last_error_message": null
    },
    {
      "fixture_id": "mt-champ-facup-001",
      "source": "fotmob",
      "source_match_id": "fixture-champ-facup-001",
      "competition_fixture_id": "comp-facup",
      "edition_fixture_id": "ed-facup-2526",
      "match_date": "2026-08-29T14:00:00Z",
      "home_team_fixture_id": "team-lee-01",
      "away_team_fixture_id": "team-shw-01",
      "match_status": "scheduled",
      "target_state": "pending_raw_fetch",
      "priority": 18,
      "discovery_source": "cup_draw",
      "source_url": null,
      "raw_json_status": "missing",
      "last_attempt_at": null,
      "last_success_at": null,
      "attempt_count": 0,
      "last_error_code": null,
      "last_error_message": null
    },
    {
      "fixture_id": "mt-mun-blocked-001",
      "source": "fotmob",
      "source_match_id": "fixture-mun-blocked-001",
      "competition_fixture_id": "comp-epl",
      "edition_fixture_id": "ed-epl-2526",
      "match_date": "2026-08-08T14:00:00Z",
      "home_team_fixture_id": "team-mun-01",
      "away_team_fixture_id": "team-tot-01",
      "match_status": "scheduled",
      "target_state": "blocked",
      "priority": 9,
      "discovery_source": "league_schedule",
      "source_url": null,
      "raw_json_status": "missing",
      "last_attempt_at": "2026-07-01T00:00:00Z",
      "last_success_at": null,
      "attempt_count": 1,
      "last_error_code": "HTTP_403",
      "last_error_message": "FotMob returned 403 on previous attempt"
    },
    {
      "fixture_id": "mt-mun-stored-001",
      "source": "fotmob",
      "source_match_id": "fixture-mun-stored-001",
      "competition_fixture_id": "comp-epl",
      "edition_fixture_id": "ed-epl-2526",
      "match_date": "2026-08-01T14:00:00Z",
      "home_team_fixture_id": "team-mun-01",
      "away_team_fixture_id": "team-eve-01",
      "match_status": "finished",
      "target_state": "raw_json_stored",
      "priority": 7,
      "discovery_source": "league_schedule",
      "source_url": null,
      "raw_json_status": "stored",
      "last_attempt_at": "2026-07-15T00:00:00Z",
      "last_success_at": "2026-07-15T00:01:00Z",
      "attempt_count": 1,
      "last_error_code": null,
      "last_error_message": null
    },
    {
      "fixture_id": "mt-eng-failed-001",
      "source": "fotmob",
      "source_match_id": "fixture-eng-failed-001",
      "competition_fixture_id": "comp-unl",
      "edition_fixture_id": "ed-unl-2526",
      "match_date": "2026-09-06T18:00:00Z",
      "home_team_fixture_id": "team-eng-01",
      "away_team_fixture_id": "team-ita-01",
      "match_status": "finished",
      "target_state": "pending_raw_fetch",
      "priority": 13,
      "discovery_source": "league_schedule",
      "source_url": null,
      "raw_json_status": "failed",
      "last_attempt_at": "2026-09-07T00:00:00Z",
      "last_success_at": null,
      "attempt_count": 1,
      "last_error_code": "JSON_PARSE_ERROR",
      "last_error_message": "SSR payload parse failure: match detail structure unexpected"
    }
  ],

  "match_target_teams": [
    {"fixture_id": "mtt-mun-epl-001-home", "match_target_fixture_id": "mt-mun-epl-001", "team_fixture_id": "team-mun-01", "role": "home"},
    {"fixture_id": "mtt-mun-epl-001-away", "match_target_fixture_id": "mt-mun-epl-001", "team_fixture_id": "team-liv-01", "role": "away"},
    {"fixture_id": "mtt-mun-facup-001-home", "match_target_fixture_id": "mt-mun-facup-001", "team_fixture_id": "team-mun-01", "role": "home"},
    {"fixture_id": "mtt-mun-facup-001-away", "match_target_fixture_id": "mt-mun-facup-001", "team_fixture_id": "team-che-01", "role": "away"},
    {"fixture_id": "mtt-mun-eflcup-001-home", "match_target_fixture_id": "mt-mun-eflcup-001", "team_fixture_id": "team-new-01", "role": "home"},
    {"fixture_id": "mtt-mun-eflcup-001-away", "match_target_fixture_id": "mt-mun-eflcup-001", "team_fixture_id": "team-mun-01", "role": "away"},
    {"fixture_id": "mtt-mun-uel-001-home", "match_target_fixture_id": "mt-mun-uel-001", "team_fixture_id": "team-mun-01", "role": "home"},
    {"fixture_id": "mtt-mun-uel-001-away", "match_target_fixture_id": "mt-mun-uel-001", "team_fixture_id": "team-rom-01", "role": "away"},
    {"fixture_id": "mtt-eng-wcq-001-home", "match_target_fixture_id": "mt-eng-wcq-001", "team_fixture_id": "team-eng-01", "role": "home"},
    {"fixture_id": "mtt-eng-wcq-001-away", "match_target_fixture_id": "mt-eng-wcq-001", "team_fixture_id": "team-pol-01", "role": "away"},
    {"fixture_id": "mtt-eng-unl-001-home", "match_target_fixture_id": "mt-eng-unl-001", "team_fixture_id": "team-ger-01", "role": "home"},
    {"fixture_id": "mtt-eng-unl-001-away", "match_target_fixture_id": "mt-eng-unl-001", "team_fixture_id": "team-eng-01", "role": "away"},
    {"fixture_id": "mtt-eng-friend-001-home", "match_target_fixture_id": "mt-eng-friend-001", "team_fixture_id": "team-eng-01", "role": "home"},
    {"fixture_id": "mtt-eng-friend-001-away", "match_target_fixture_id": "mt-eng-friend-001", "team_fixture_id": "team-bra-01", "role": "away"},
    {"fixture_id": "mtt-jpn-j1-001-home", "match_target_fixture_id": "mt-jpn-j1-001", "team_fixture_id": "team-kas-01", "role": "home"},
    {"fixture_id": "mtt-jpn-j1-001-away", "match_target_fixture_id": "mt-jpn-j1-001", "team_fixture_id": "team-yok-01", "role": "away"},
    {"fixture_id": "mtt-jpn-empcup-001-home", "match_target_fixture_id": "mt-jpn-empcup-001", "team_fixture_id": "team-kas-01", "role": "home"},
    {"fixture_id": "mtt-jpn-empcup-001-away", "match_target_fixture_id": "mt-jpn-empcup-001", "team_fixture_id": "team-ura-01", "role": "away"},
    {"fixture_id": "mtt-champ-001-home", "match_target_fixture_id": "mt-champ-001", "team_fixture_id": "team-lee-01", "role": "home"},
    {"fixture_id": "mtt-champ-001-away", "match_target_fixture_id": "mt-champ-001", "team_fixture_id": "team-sun-01", "role": "away"},
    {"fixture_id": "mtt-champ-facup-001-home", "match_target_fixture_id": "mt-champ-facup-001", "team_fixture_id": "team-lee-01", "role": "home"},
    {"fixture_id": "mtt-champ-facup-001-away", "match_target_fixture_id": "mt-champ-facup-001", "team_fixture_id": "team-shw-01", "role": "away"},
    {"fixture_id": "mtt-mun-blocked-001-home", "match_target_fixture_id": "mt-mun-blocked-001", "team_fixture_id": "team-mun-01", "role": "home"},
    {"fixture_id": "mtt-mun-blocked-001-away", "match_target_fixture_id": "mt-mun-blocked-001", "team_fixture_id": "team-tot-01", "role": "away"},
    {"fixture_id": "mtt-mun-stored-001-home", "match_target_fixture_id": "mt-mun-stored-001", "team_fixture_id": "team-mun-01", "role": "home"},
    {"fixture_id": "mtt-mun-stored-001-away", "match_target_fixture_id": "mt-mun-stored-001", "team_fixture_id": "team-eve-01", "role": "away"},
    {"fixture_id": "mtt-eng-failed-001-home", "match_target_fixture_id": "mt-eng-failed-001", "team_fixture_id": "team-eng-01", "role": "home"},
    {"fixture_id": "mtt-eng-failed-001-away", "match_target_fixture_id": "mt-eng-failed-001", "team_fixture_id": "team-ita-01", "role": "away"}
  ],

  "source_identities": [
    {"fixture_id": "si-team-mun", "source": "fotmob", "entity_type": "team", "entity_fixture_id": "team-mun-01", "source_entity_id": "fixture-mun-01"},
    {"fixture_id": "si-team-eng", "source": "fotmob", "entity_type": "team", "entity_fixture_id": "team-eng-01", "source_entity_id": "fixture-eng-01"},
    {"fixture_id": "si-team-kas", "source": "fotmob", "entity_type": "team", "entity_fixture_id": "team-kas-01", "source_entity_id": "fixture-kas-01"},
    {"fixture_id": "si-team-lee", "source": "fotmob", "entity_type": "team", "entity_fixture_id": "team-lee-01", "source_entity_id": "fixture-lee-01"},
    {"fixture_id": "si-comp-epl", "source": "fotmob", "entity_type": "competition", "entity_fixture_id": "comp-epl", "source_entity_id": "fixture-comp-epl"},
    {"fixture_id": "si-comp-facup", "source": "fotmob", "entity_type": "competition", "entity_fixture_id": "comp-facup", "source_entity_id": "fixture-comp-facup"},
    {"fixture_id": "si-comp-uel", "source": "fotmob", "entity_type": "competition", "entity_fixture_id": "comp-uel", "source_entity_id": "fixture-comp-uel"},
    {"fixture_id": "si-comp-wcq", "source": "fotmob", "entity_type": "competition", "entity_fixture_id": "comp-wcq", "source_entity_id": "fixture-comp-wcq"},
    {"fixture_id": "si-comp-j1", "source": "fotmob", "entity_type": "competition", "entity_fixture_id": "comp-j1", "source_entity_id": "fixture-comp-j1"},
    {"fixture_id": "si-comp-champ", "source": "fotmob", "entity_type": "competition", "entity_fixture_id": "comp-champ", "source_entity_id": "fixture-comp-champ"}
  ]
}
